Workbook

Sheet Welcome
B2: THE ULTIMATE BUDGET PLANNER
B4: A complete system for planning, tracking & growing your money
B6: YEAR
B7: 2026
B9: WHAT'S INSIDE
B10: Dashboard | C10: Your at-a-glance yearly overview with automatic charts.
B11: Jan - Dec Tabs | C11: A full monthly budget: plan it, then track what actually happened.
B12: Transactions | C12: Log every purchase once — everything else updates itself.
B13: Annual Overview | C13: All 12 months side-by-side, so trends jump right out.
B14: Debt Payoff Tracker | C14: See exactly when each debt will hit zero.
B15: Savings Goals | C15: Turn 'someday' goals into a monthly savings number.
B17: HOW TO USE THIS PLANNER
B18: 1. Start on the Transactions tab and log your income & expenses as they happen (or all at once for the month).
B19: 2. Open the matching month tab (Jan, Feb, ...) and fill in the yellow BUDGETED column with your plan for each category.
B20: 3. The ACTUAL and VARIANCE columns fill in automatically from your Transactions log — no manual math required.
B21: 4. Check the Dashboard any time for a live picture of the whole year.
B22: 5. Use the Debt Payoff and Savings Goals tabs to plan beyond the month-to-month.
B24: COLOR KEY
C25: Yellow / gold cells = type your own numbers here
C26: White cells with a formula = calculated automatically, don't overwrite
C27: Teal band = Income section
C28: Blush band = Variable Expenses section
B31: Tip: right-click any sheet tab to duplicate it if you'd like extra copies (e.g. per bank account).

Sheet Dashboard
B2: ="YEARLY DASHBOARD — "&Welcome!$B$7 -> YEARLY DASHBOARD — 2026
B4: TOTAL INCOME (YTD) | C4: TOTAL EXPENSES (YTD) | D4: TOTAL SAVED (YTD) | E4: NET CASH FLOW (YTD)
B5: ='Annual Overview'!N50 -> 6850 | C5: ='Annual Overview'!N51 -> 1958.47 | D5: ='Annual Overview'!N52 -> 450 | E5: ='Annual Overview'!N53 -> 4441.53
B8: SAVINGS RATE (YTD) | D8: AVG MONTHLY SPEND
B9: ='Annual Overview'!N52/'Annual Overview'!N50 -> 0.065693431 | D9: ='Annual Overview'!N51/12 -> 163.20583
H11: Category | I11: YTD Total
H12: Rent / Mortgage | I12: ='Annual Overview'!N15 -> 1450
H13: Utilities | I13: ='Annual Overview'!N16 -> 165.32
H14: Insurance | I14: ='Annual Overview'!N17 -> 0
H15: Phone Bill | I15: ='Annual Overview'!N18 -> 0
H16: Internet | I16: ='Annual Overview'!N19 -> 0
H17: Subscriptions | I17: ='Annual Overview'!N20 -> 24.98
H18: Car Payment | I18: ='Annual Overview'!N21 -> 0
H19: Loan Payments | I19: ='Annual Overview'!N22 -> 0
H20: Groceries | I20: ='Annual Overview'!N26 -> 211.07
H21: Dining Out | I21: ='Annual Overview'!N27 -> 62.1
H22: Transportation / Gas | I22: ='Annual Overview'!N28 -> 45
H23: Entertainment | I23: ='Annual Overview'!N29 -> 0
H24: Shopping | I24: ='Annual Overview'!N30 -> 0
H25: Personal Care | I25: ='Annual Overview'!N31 -> 0
H26: Health / Medical | I26: ='Annual Overview'!N32 -> 0
H27: Pet Care | I27: ='Annual Overview'!N33 -> 0
H28: Childcare | I28: ='Annual Overview'!N34 -> 0
H29: Gifts & Donations | I29: ='Annual Overview'!N35 -> 0
H30: Travel | I30: ='Annual Overview'!N36 -> 0
H31: Miscellaneous | I31: ='Annual Overview'!N37 -> 0

Sheet Jan
A1: ="JANUARY"&" "&Welcome!$B$7&" BUDGET" -> JANUARY 2026 BUDGET
A2: Plan it in BUDGETED, then let ACTUAL fill in from your Transactions log.
A4: CATEGORY | B4: BUDGETED | C4: ACTUAL | D4: VARIANCE
A5: INCOME
A6: Salary | B6: 6400 | C6: =SUMIFS(Transactions!$E$4:$E$400,Transactions!$C$4:$C$400,$A6,Transactions!$F$4:$F$400,1) -> 6400 | D6: =C6-B6 -> 0
A7: Freelance / Side Hustle | B7: 400 | C7: =SUMIFS(Transactions!$E$4:$E$400,Transactions!$C$4:$C$400,$A7,Transactions!$F$4:$F$400,1) -> 450 | D7: =C7-B7 -> 50
A8: Bonus | B8: 0 | C8: =SUMIFS(Transactions!$E$4:$E$400,Transactions!$C$4:$C$400,$A8,Transactions!$F$4:$F$400,1) -> 0 | D8: =C8-B8 -> 0
A9: Investment Income | B9: 0 | C9: =SUMIFS(Transactions!$E$4:$E$400,Transactions!$C$4:$C$400,$A9,Transactions!$F$4:$F$400,1) -> 0 | D9: =C9-B9 -> 0
A10: Gifts Received | B10: 0 | C10: =SUMIFS(Transactions!$E$4:$E$400,Transactions!$C$4:$C$400,$A10,Transactions!$F$4:$F$400,1) -> 0 | D10: =C10-B10 -> 0
A11: Other Income | B11: 0 | C11: =SUMIFS(Transactions!$E$4:$E$400,Transactions!$C$4:$C$400,$A11,Transactions!$F$4:$F$400,1) -> 0 | D11: =C11-B11 -> 0
A12: Total Income | B12: =SUM(B6:B11) -> 6800 | C12: =SUM(C6:C11) -> 6850 | D12: =SUM(D6:D11) -> 50
A14: FIXED EXPENSES
A15: Rent / Mortgage | B15: 1450 | C15: =SUMIFS(Transactions!$E$4:$E$400,Transactions!$C$4:$C$400,$A15,Transactions!$F$4:$F$400,1) -> 1450 | D15: =C15-B15 -> 0
A16: Utilities | B16: 180 | C16: =SUMIFS(Transactions!$E$4:$E$400,Transactions!$C$4:$C$400,$A16,Transactions!$F$4:$F$400,1) -> 165.32 | D16: =C16-B16 -> -14.68
A17: Insurance | B17: 120 | C17: =SUMIFS(Transactions!$E$4:$E$400,Transactions!$C$4:$C$400,$A17,Transactions!$F$4:$F$400,1) -> 0 | D17: =C17-B17 -> -120
A18: Phone Bill | B18: 65 | C18: =SUMIFS(Transactions!$E$4:$E$400,Transactions!$C$4:$C$400,$A18,Transactions!$F$4:$F$400,1) -> 0 | D18: =C18-B18 -> -65
A19: Internet | B19: 60 | C19: =SUMIFS(Transactions!$E$4:$E$400,Transactions!$C$4:$C$400,$A19,Transactions!$F$4:$F$400,1) -> 0 | D19: =C19-B19 -> -60
A20: Subscriptions | B20: 35 | C20: =SUMIFS(Transactions!$E$4:$E$400,Transactions!$C$4:$C$400,$A20,Transactions!$F$4:$F$400,1) -> 24.98 | D20: =C20-B20 -> -10.02
A21: Car Payment | B21: 320 | C21: =SUMIFS(Transactions!$E$4:$E$400,Transactions!$C$4:$C$400,$A21,Transactions!$F$4:$F$400,1) -> 0 | D21: =C21-B21 -> -320
A22: Loan Payments | B22: 150 | C22: =SUMIFS(Transactions!$E$4:$E$400,Transactions!$C$4:$C$400,$A22,Transactions!$F$4:$F$400,1) -> 0 | D22: =C22-B22 -> -150
A23: Total Fixed Expenses | B23: =SUM(B15:B22) -> 2380 | C23: =SUM(C15:C22) -> 1640.3 | D23: =SUM(D15:D22) -> -739.7
A25: VARIABLE EXPENSES
A26: Groceries | B26: 450 | C26: =SUMIFS(Transactions!$E$4:$E$400,Transactions!$C$4:$C$400,$A26,Transactions!$F$4:$F$400,1) -> 211.07 | D26: =C26-B26 -> -238.93
A27: Dining Out | B27: 150 | C27: =SUMIFS(Transactions!$E$4:$E$400,Transactions!$C$4:$C$400,$A27,Transactions!$F$4:$F$400,1) -> 62.1 | D27: =C27-B27 -> -87.9
A28: Transportation / Gas | B28: 120 | C28: =SUMIFS(Transactions!$E$4:$E$400,Transactions!$C$4:$C$400,$A28,Transactions!$F$4:$F$400,1) -> 45 | D28: =C28-B28 -> -75
A29: Entertainment | B29: 80 | C29: =SUMIFS(Transactions!$E$4:$E$400,Transactions!$C$4:$C$400,$A29,Transactions!$F$4:$F$400,1) -> 0 | D29: =C29-B29 -> -80
A30: Shopping | B30: 100 | C30: =SUMIFS(Transactions!$E$4:$E$400,Transactions!$C$4:$C$400,$A30,Transactions!$F$4:$F$400,1) -> 0 | D30: =C30-B30 -> -100
A31: Personal Care | B31: 50 | C31: =SUMIFS(Transactions!$E$4:$E$400,Transactions!$C$4:$C$400,$A31,Transactions!$F$4:$F$400,1) -> 0 | D31: =C31-B31 -> -50
A32: Health / Medical | B32: 60 | C32: =SUMIFS(Transactions!$E$4:$E$400,Transactions!$C$4:$C$400,$A32,Transactions!$F$4:$F$400,1) -> 0 | D32: =C32-B32 -> -60
A33: Pet Care | B33: 40 | C33: =SUMIFS(Transactions!$E$4:$E$400,Transactions!$C$4:$C$400,$A33,Transactions!$F$4:$F$400,1) -> 0 | D33: =C33-B33 -> -40
A34: Childcare | B34: 0 | C34: =SUMIFS(Transactions!$E$4:$E$400,Transactions!$C$4:$C$400,$A34,Transactions!$F$4:$F$400,1) -> 0 | D34: =C34-B34 -> 0
A35: Gifts & Donations | B35: 40 | C35: =SUMIFS(Transactions!$E$4:$E$400,Transactions!$C$4:$C$400,$A35,Transactions!$F$4:$F$400,1) -> 0 | D35: =C35-B35 -> -40
A36: Travel | B36: 0 | C36: =SUMIFS(Transactions!$E$4:$E$400,Transactions!$C$4:$C$400,$A36,Transactions!$F$4:$F$400,1) -> 0 | D36: =C36-B36 -> 0
A37: Miscellaneous | B37: 50 | C37: =SUMIFS(Transactions!$E$4:$E$400,Transactions!$C$4:$C$400,$A37,Transactions!$F$4:$F$400,1) -> 0 | D37: =C37-B37 -> -50
A38: Total Variable Expenses | B38: =SUM(B26:B37) -> 1140 | C38: =SUM(C26:C37) -> 318.17 | D38: =SUM(D26:D37) -> -821.83
A40: SAVINGS & DEBT
A41: Emergency Fund | B41: 300 | C41: =SUMIFS(Transactions!$E$4:$E$400,Transactions!$C$4:$C$400,$A41,Transactions!$F$4:$F$400,1) -> 300 | D41: =C41-B41 -> 0
A42: Retirement Savings | B42: 200 | C42: =SUMIFS(Transactions!$E$4:$E$400,Transactions!$C$4:$C$400,$A42,Transactions!$F$4:$F$400,1) -> 0 | D42: =C42-B42 -> -200
A43: Investment Contributions | B43: 0 | C43: =SUMIFS(Transactions!$E$4:$E$400,Transactions!$C$4:$C$400,$A43,Transactions!$F$4:$F$400,1) -> 0 | D43: =C43-B43 -> 0
A44: Debt Payoff | B44: 150 | C44: =SUMIFS(Transactions!$E$4:$E$400,Transactions!$C$4:$C$400,$A44,Transactions!$F$4:$F$400,1) -> 150 | D44: =C44-B44 -> 0
A45: Vacation Fund | B45: 50 | C45: =SUMIFS(Transactions!$E$4:$E$400,Transactions!$C$4:$C$400,$A45,Transactions!$F$4:$F$400,1) -> 0 | D45: =C45-B45 -> -50
A46: Other Savings | B46: 0 | C46: =SUMIFS(Transactions!$E$4:$E$400,Transactions!$C$4:$C$400,$A46,Transactions!$F$4:$F$400,1) -> 0 | D46: =C46-B46 -> 0
A47: Total Savings & Debt | B47: =SUM(B41:B46) -> 700 | C47: =SUM(C41:C46) -> 450 | D47: =SUM(D41:D46) -> -250
A49: MONTH SUMMARY
A50: Total Income | B50: =B12 -> 6800 | C50: =C12 -> 6850 | D50: =C50-B50 -> 50
A51: Total Expenses (Fixed + Variable) | B51: =B23+B38 -> 3520 | C51: =C23+C38 -> 1958.47 | D51: =C51-B51 -> -1561.53
A52: Total Savings & Debt Payments | B52: =B47 -> 700 | C52: =C47 -> 450 | D52: =C52-B52 -> -250
A53: NET REMAINING (Income - Everything Else) | B53: =B50-B51-B52 -> 2580 | C53: =C50-C51-C52 -> 4441.53 | D53: =C53-B53 -> 1861.53

Sheet Feb
A1: ="FEBRUARY"&" "&Welcome!$B$7&" BUDGET" -> FEBRUARY 2026 BUDGET
A2: Plan it in BUDGETED, then let ACTUAL fill in from your Transactions log.
A4: CATEGORY | B4: BUDGETED | C4: ACTUAL | D4: VARIANCE
A5: INCOME
A6: Salary | B6: 0 | C6: =SUMIFS(Transactions!$E$4:$E$400,Transactions!$C$4:$C$400,$A6,Transactions!$F$4:$F$400,2) -> 0 | D6: =C6-B6 -> 0
A7: Freelance / Side Hustle | B7: 0 | C7: =SUMIFS(Transactions!$E$4:$E$400,Transactions!$C$4:$C$400,$A7,Transactions!$F$4:$F$400,2) -> 0 | D7: =C7-B7 -> 0
A8: Bonus | B8: 0 | C8: =SUMIFS(Transactions!$E$4:$E$400,Transactions!$C$4:$C$400,$A8,Transactions!$F$4:$F$400,2) -> 0 | D8: =C8-B8 -> 0
A9: Investment Income | B9: 0 | C9: =SUMIFS(Transactions!$E$4:$E$400,Transactions!$C$4:$C$400,$A9,Transactions!$F$4:$F$400,2) -> 0 | D9: =C9-B9 -> 0
A10: Gifts Received | B10: 0 | C10: =SUMIFS(Transactions!$E$4:$E$400,Transactions!$C$4:$C$400,$A10,Transactions!$F$4:$F$400,2) -> 0 | D10: =C10-B10 -> 0
A11: Other Income | B11: 0 | C11: =SUMIFS(Transactions!$E$4:$E$400,Transactions!$C$4:$C$400,$A11,Transactions!$F$4:$F$400,2) -> 0 | D11: =C11-B11 -> 0
A12: Total Income | B12: =SUM(B6:B11) -> 0 | C12: =SUM(C6:C11) -> 0 | D12: =SUM(D6:D11) -> 0
A14: FIXED EXPENSES
A15: Rent / Mortgage | B15: 0 | C15: =SUMIFS(Transactions!$E$4:$E$400,Transactions!$C$4:$C$400,$A15,Transactions!$F$4:$F$400,2) -> 0 | D15: =C15-B15 -> 0
A16: Utilities | B16: 0 | C16: =SUMIFS(Transactions!$E$4:$E$400,Transactions!$C$4:$C$400,$A16,Transactions!$F$4:$F$400,2) -> 0 | D16: =C16-B16 -> 0
A17: Insurance | B17: 0 | C17: =SUMIFS(Transactions!$E$4:$E$400,Transactions!$C$4:$C$400,$A17,Transactions!$F$4:$F$400,2) -> 0 | D17: =C17-B17 -> 0
A18: Phone Bill | B18: 0 | C18: =SUMIFS(Transactions!$E$4:$E$400,Transactions!$C$4:$C$400,$A18,Transactions!$F$4:$F$400,2) -> 0 | D18: =C18-B18 -> 0
A19: Internet | B19: 0 | C19: =SUMIFS(Transactions!$E$4:$E$400,Transactions!$C$4:$C$400,$A19,Transactions!$F$4:$F$400,2) -> 0 | D19: =C19-B19 -> 0
A20: Subscriptions | B20: 0 | C20: =SUMIFS(Transactions!$E$4:$E$400,Transactions!$C$4:$C$400,$A20,Transactions!$F$4:$F$400,2) -> 0 | D20: =C20-B20 -> 0
A21: Car Payment | B21: 0 | C21: =SUMIFS(Transactions!$E$4:$E$400,Transactions!$C$4:$C$400,$A21,Transactions!$F$4:$F$400,2) -> 0 | D21: =C21-B21 -> 0
A22: Loan Payments | B22: 0 | C22: =SUMIFS(Transactions!$E$4:$E$400,Transactions!$C$4:$C$400,$A22,Transactions!$F$4:$F$400,2) -> 0 | D22: =C22-B22 -> 0
A23: Total Fixed Expenses | B23: =SUM(B15:B22) -> 0 | C23: =SUM(C15:C22) -> 0 | D23: =SUM(D15:D22) -> 0
A25: VARIABLE EXPENSES
A26: Groceries | B26: 0 | C26: =SUMIFS(Transactions!$E$4:$E$400,Transactions!$C$4:$C$400,$A26,Transactions!$F$4:$F$400,2) -> 0 | D26: =C26-B26 -> 0
A27: Dining Out | B27: 0 | C27: =SUMIFS(Transactions!$E$4:$E$400,Transactions!$C$4:$C$400,$A27,Transactions!$F$4:$F$400,2) -> 0 | D27: =C27-B27 -> 0
A28: Transportation / Gas | B28: 0 | C28: =SUMIFS(Transactions!$E$4:$E$400,Transactions!$C$4:$C$400,$A28,Transactions!$F$4:$F$400,2) -> 0 | D28: =C28-B28 -> 0
A29: Entertainment | B29: 0 | C29: =SUMIFS(Transactions!$E$4:$E$400,Transactions!$C$4:$C$400,$A29,Transactions!$F$4:$F$400,2) -> 0 | D29: =C29-B29 -> 0
A30: Shopping | B30: 0 | C30: =SUMIFS(Transactions!$E$4:$E$400,Transactions!$C$4:$C$400,$A30,Transactions!$F$4:$F$400,2) -> 0 | D30: =C30-B30 -> 0
A31: Personal Care | B31: 0 | C31: =SUMIFS(Transactions!$E$4:$E$400,Transactions!$C$4:$C$400,$A31,Transactions!$F$4:$F$400,2) -> 0 | D31: =C31-B31 -> 0
A32: Health / Medical | B32: 0 | C32: =SUMIFS(Transactions!$E$4:$E$400,Transactions!$C$4:$C$400,$A32,Transactions!$F$4:$F$400,2) -> 0 | D32: =C32-B32 -> 0
A33: Pet Care | B33: 0 | C33: =SUMIFS(Transactions!$E$4:$E$400,Transactions!$C$4:$C$400,$A33,Transactions!$F$4:$F$400,2) -> 0 | D33: =C33-B33 -> 0
A34: Childcare | B34: 0 | C34: =SUMIFS(Transactions!$E$4:$E$400,Transactions!$C$4:$C$400,$A34,Transactions!$F$4:$F$400,2) -> 0 | D34: =C34-B34 -> 0
A35: Gifts & Donations | B35: 0 | C35: =SUMIFS(Transactions!$E$4:$E$400,Transactions!$C$4:$C$400,$A35,Transactions!$F$4:$F$400,2) -> 0 | D35: =C35-B35 -> 0
A36: Travel | B36: 0 | C36: =SUMIFS(Transactions!$E$4:$E$400,Transactions!$C$4:$C$400,$A36,Transactions!$F$4:$F$400,2) -> 0 | D36: =C36-B36 -> 0
A37: Miscellaneous | B37: 0 | C37: =SUMIFS(Transactions!$E$4:$E$400,Transactions!$C$4:$C$400,$A37,Transactions!$F$4:$F$400,2) -> 0 | D37: =C37-B37 -> 0
A38: Total Variable Expenses | B38: =SUM(B26:B37) -> 0 | C38: =SUM(C26:C37) -> 0 | D38: =SUM(D26:D37) -> 0
A40: SAVINGS & DEBT
A41: Emergency Fund | B41: 0 | C41: =SUMIFS(Transactions!$E$4:$E$400,Transactions!$C$4:$C$400,$A41,Transactions!$F$4:$F$400,2) -> 0 | D41: =C41-B41 -> 0
A42: Retirement Savings | B42: 0 | C42: =SUMIFS(Transactions!$E$4:$E$400,Transactions!$C$4:$C$400,$A42,Transactions!$F$4:$F$400,2) -> 0 | D42: =C42-B42 -> 0
A43: Investment Contributions | B43: 0 | C43: =SUMIFS(Transactions!$E$4:$E$400,Transactions!$C$4:$C$400,$A43,Transactions!$F$4:$F$400,2) -> 0 | D43: =C43-B43 -> 0
A44: Debt Payoff | B44: 0 | C44: =SUMIFS(Transactions!$E$4:$E$400,Transactions!$C$4:$C$400,$A44,Transactions!$F$4:$F$400,2) -> 0 | D44: =C44-B44 -> 0
A45: Vacation Fund | B45: 0 | C45: =SUMIFS(Transactions!$E$4:$E$400,Transactions!$C$4:$C$400,$A45,Transactions!$F$4:$F$400,2) -> 0 | D45: =C45-B45 -> 0
A46: Other Savings | B46: 0 | C46: =SUMIFS(Transactions!$E$4:$E$400,Transactions!$C$4:$C$400,$A46,Transactions!$F$4:$F$400,2) -> 0 | D46: =C46-B46 -> 0
A47: Total Savings & Debt | B47: =SUM(B41:B46) -> 0 | C47: =SUM(C41:C46) -> 0 | D47: =SUM(D41:D46) -> 0
A49: MONTH SUMMARY
A50: Total Income | B50: =B12 -> 0 | C50: =C12 -> 0 | D50: =C50-B50 -> 0
A51: Total Expenses (Fixed + Variable) | B51: =B23+B38 -> 0 | C51: =C23+C38 -> 0 | D51: =C51-B51 -> 0
A52: Total Savings & Debt Payments | B52: =B47 -> 0 | C52: =C47 -> 0 | D52: =C52-B52 -> 0
A53: NET REMAINING (Income - Everything Else) | B53: =B50-B51-B52 -> 0 | C53: =C50-C51-C52 -> 0 | D53: =C53-B53 -> 0

Sheet Mar
A1: ="MARCH"&" "&Welcome!$B$7&" BUDGET" -> MARCH 2026 BUDGET
A2: Plan it in BUDGETED, then let ACTUAL fill in from your Transactions log.
A4: CATEGORY | B4: BUDGETED | C4: ACTUAL | D4: VARIANCE
A5: INCOME
A6: Salary | B6: 0 | C6: =SUMIFS(Transactions!$E$4:$E$400,Transactions!$C$4:$C$400,$A6,Transactions!$F$4:$F$400,3) -> 0 | D6: =C6-B6 -> 0
A7: Freelance / Side Hustle | B7: 0 | C7: =SUMIFS(Transactions!$E$4:$E$400,Transactions!$C$4:$C$400,$A7,Transactions!$F$4:$F$400,3) -> 0 | D7: =C7-B7 -> 0
A8: Bonus | B8: 0 | C8: =SUMIFS(Transactions!$E$4:$E$400,Transactions!$C$4:$C$400,$A8,Transactions!$F$4:$F$400,3) -> 0 | D8: =C8-B8 -> 0
A9: Investment Income | B9: 0 | C9: =SUMIFS(Transactions!$E$4:$E$400,Transactions!$C$4:$C$400,$A9,Transactions!$F$4:$F$400,3) -> 0 | D9: =C9-B9 -> 0
A10: Gifts Received | B10: 0 | C10: =SUMIFS(Transactions!$E$4:$E$400,Transactions!$C$4:$C$400,$A10,Transactions!$F$4:$F$400,3) -> 0 | D10: =C10-B10 -> 0
A11: Other Income | B11: 0 | C11: =SUMIFS(Transactions!$E$4:$E$400,Transactions!$C$4:$C$400,$A11,Transactions!$F$4:$F$400,3) -> 0 | D11: =C11-B11 -> 0
A12: Total Income | B12: =SUM(B6:B11) -> 0 | C12: =SUM(C6:C11) -> 0 | D12: =SUM(D6:D11) -> 0
A14: FIXED EXPENSES
A15: Rent / Mortgage | B15: 0 | C15: =SUMIFS(Transactions!$E$4:$E$400,Transactions!$C$4:$C$400,$A15,Transactions!$F$4:$F$400,3) -> 0 | D15: =C15-B15 -> 0
A16: Utilities | B16: 0 | C16: =SUMIFS(Transactions!$E$4:$E$400,Transactions!$C$4:$C$400,$A16,Transactions!$F$4:$F$400,3) -> 0 | D16: =C16-B16 -> 0
A17: Insurance | B17: 0 | C17: =SUMIFS(Transactions!$E$4:$E$400,Transactions!$C$4:$C$400,$A17,Transactions!$F$4:$F$400,3) -> 0 | D17: =C17-B17 -> 0
A18: Phone Bill | B18: 0 | C18: =SUMIFS(Transactions!$E$4:$E$400,Transactions!$C$4:$C$400,$A18,Transactions!$F$4:$F$400,3) -> 0 | D18: =C18-B18 -> 0
A19: Internet | B19: 0 | C19: =SUMIFS(Transactions!$E$4:$E$400,Transactions!$C$4:$C$400,$A19,Transactions!$F$4:$F$400,3) -> 0 | D19: =C19-B19 -> 0
A20: Subscriptions | B20: 0 | C20: =SUMIFS(Transactions!$E$4:$E$400,Transactions!$C$4:$C$400,$A20,Transactions!$F$4:$F$400,3) -> 0 | D20: =C20-B20 -> 0
A21: Car Payment | B21: 0 | C21: =SUMIFS(Transactions!$E$4:$E$400,Transactions!$C$4:$C$400,$A21,Transactions!$F$4:$F$400,3) -> 0 | D21: =C21-B21 -> 0
A22: Loan Payments | B22: 0 | C22: =SUMIFS(Transactions!$E$4:$E$400,Transactions!$C$4:$C$400,$A22,Transactions!$F$4:$F$400,3) -> 0 | D22: =C22-B22 -> 0
A23: Total Fixed Expenses | B23: =SUM(B15:B22) -> 0 | C23: =SUM(C15:C22) -> 0 | D23: =SUM(D15:D22) -> 0
A25: VARIABLE EXPENSES
A26: Groceries | B26: 0 | C26: =SUMIFS(Transactions!$E$4:$E$400,Transactions!$C$4:$C$400,$A26,Transactions!$F$4:$F$400,3) -> 0 | D26: =C26-B26 -> 0
A27: Dining Out | B27: 0 | C27: =SUMIFS(Transactions!$E$4:$E$400,Transactions!$C$4:$C$400,$A27,Transactions!$F$4:$F$400,3) -> 0 | D27: =C27-B27 -> 0
A28: Transportation / Gas | B28: 0 | C28: =SUMIFS(Transactions!$E$4:$E$400,Transactions!$C$4:$C$400,$A28,Transactions!$F$4:$F$400,3) -> 0 | D28: =C28-B28 -> 0
A29: Entertainment | B29: 0 | C29: =SUMIFS(Transactions!$E$4:$E$400,Transactions!$C$4:$C$400,$A29,Transactions!$F$4:$F$400,3) -> 0 | D29: =C29-B29 -> 0
A30: Shopping | B30: 0 | C30: =SUMIFS(Transactions!$E$4:$E$400,Transactions!$C$4:$C$400,$A30,Transactions!$F$4:$F$400,3) -> 0 | D30: =C30-B30 -> 0
A31: Personal Care | B31: 0 | C31: =SUMIFS(Transactions!$E$4:$E$400,Transactions!$C$4:$C$400,$A31,Transactions!$F$4:$F$400,3) -> 0 | D31: =C31-B31 -> 0
A32: Health / Medical | B32: 0 | C32: =SUMIFS(Transactions!$E$4:$E$400,Transactions!$C$4:$C$400,$A32,Transactions!$F$4:$F$400,3) -> 0 | D32: =C32-B32 -> 0
A33: Pet Care | B33: 0 | C33: =SUMIFS(Transactions!$E$4:$E$400,Transactions!$C$4:$C$400,$A33,Transactions!$F$4:$F$400,3) -> 0 | D33: =C33-B33 -> 0
A34: Childcare | B34: 0 | C34: =SUMIFS(Transactions!$E$4:$E$400,Transactions!$C$4:$C$400,$A34,Transactions!$F$4:$F$400,3) -> 0 | D34: =C34-B34 -> 0
A35: Gifts & Donations | B35: 0 | C35: =SUMIFS(Transactions!$E$4:$E$400,Transactions!$C$4:$C$400,$A35,Transactions!$F$4:$F$400,3) -> 0 | D35: =C35-B35 -> 0
A36: Travel | B36: 0 | C36: =SUMIFS(Transactions!$E$4:$E$400,Transactions!$C$4:$C$400,$A36,Transactions!$F$4:$F$400,3) -> 0 | D36: =C36-B36 -> 0
A37: Miscellaneous | B37: 0 | C37: =SUMIFS(Transactions!$E$4:$E$400,Transactions!$C$4:$C$400,$A37,Transactions!$F$4:$F$400,3) -> 0 | D37: =C37-B37 -> 0
A38: Total Variable Expenses | B38: =SUM(B26:B37) -> 0 | C38: =SUM(C26:C37) -> 0 | D38: =SUM(D26:D37) -> 0
A40: SAVINGS & DEBT
A41: Emergency Fund | B41: 0 | C41: =SUMIFS(Transactions!$E$4:$E$400,Transactions!$C$4:$C$400,$A41,Transactions!$F$4:$F$400,3) -> 0 | D41: =C41-B41 -> 0
A42: Retirement Savings | B42: 0 | C42: =SUMIFS(Transactions!$E$4:$E$400,Transactions!$C$4:$C$400,$A42,Transactions!$F$4:$F$400,3) -> 0 | D42: =C42-B42 -> 0
A43: Investment Contributions | B43: 0 | C43: =SUMIFS(Transactions!$E$4:$E$400,Transactions!$C$4:$C$400,$A43,Transactions!$F$4:$F$400,3) -> 0 | D43: =C43-B43 -> 0
A44: Debt Payoff | B44: 0 | C44: =SUMIFS(Transactions!$E$4:$E$400,Transactions!$C$4:$C$400,$A44,Transactions!$F$4:$F$400,3) -> 0 | D44: =C44-B44 -> 0
A45: Vacation Fund | B45: 0 | C45: =SUMIFS(Transactions!$E$4:$E$400,Transactions!$C$4:$C$400,$A45,Transactions!$F$4:$F$400,3) -> 0 | D45: =C45-B45 -> 0
A46: Other Savings | B46: 0 | C46: =SUMIFS(Transactions!$E$4:$E$400,Transactions!$C$4:$C$400,$A46,Transactions!$F$4:$F$400,3) -> 0 | D46: =C46-B46 -> 0
A47: Total Savings & Debt | B47: =SUM(B41:B46) -> 0 | C47: =SUM(C41:C46) -> 0 | D47: =SUM(D41:D46) -> 0
A49: MONTH SUMMARY
A50: Total Income | B50: =B12 -> 0 | C50: =C12 -> 0 | D50: =C50-B50 -> 0
A51: Total Expenses (Fixed + Variable) | B51: =B23+B38 -> 0 | C51: =C23+C38 -> 0 | D51: =C51-B51 -> 0
A52: Total Savings & Debt Payments | B52: =B47 -> 0 | C52: =C47 -> 0 | D52: =C52-B52 -> 0
A53: NET REMAINING (Income - Everything Else) | B53: =B50-B51-B52 -> 0 | C53: =C50-C51-C52 -> 0 | D53: =C53-B53 -> 0

Sheet Apr
A1: ="APRIL"&" "&Welcome!$B$7&" BUDGET" -> APRIL 2026 BUDGET
A2: Plan it in BUDGETED, then let ACTUAL fill in from your Transactions log.
A4: CATEGORY | B4: BUDGETED | C4: ACTUAL | D4: VARIANCE
A5: INCOME
A6: Salary | B6: 0 | C6: =SUMIFS(Transactions!$E$4:$E$400,Transactions!$C$4:$C$400,$A6,Transactions!$F$4:$F$400,4) -> 0 | D6: =C6-B6 -> 0
A7: Freelance / Side Hustle | B7: 0 | C7: =SUMIFS(Transactions!$E$4:$E$400,Transactions!$C$4:$C$400,$A7,Transactions!$F$4:$F$400,4) -> 0 | D7: =C7-B7 -> 0
A8: Bonus | B8: 0 | C8: =SUMIFS(Transactions!$E$4:$E$400,Transactions!$C$4:$C$400,$A8,Transactions!$F$4:$F$400,4) -> 0 | D8: =C8-B8 -> 0
A9: Investment Income | B9: 0 | C9: =SUMIFS(Transactions!$E$4:$E$400,Transactions!$C$4:$C$400,$A9,Transactions!$F$4:$F$400,4) -> 0 | D9: =C9-B9 -> 0
A10: Gifts Received | B10: 0 | C10: =SUMIFS(Transactions!$E$4:$E$400,Transactions!$C$4:$C$400,$A10,Transactions!$F$4:$F$400,4) -> 0 | D10: =C10-B10 -> 0
A11: Other Income | B11: 0 | C11: =SUMIFS(Transactions!$E$4:$E$400,Transactions!$C$4:$C$400,$A11,Transactions!$F$4:$F$400,4) -> 0 | D11: =C11-B11 -> 0
A12: Total Income | B12: =SUM(B6:B11) -> 0 | C12: =SUM(C6:C11) -> 0 | D12: =SUM(D6:D11) -> 0
A14: FIXED EXPENSES
A15: Rent / Mortgage | B15: 0 | C15: =SUMIFS(Transactions!$E$4:$E$400,Transactions!$C$4:$C$400,$A15,Transactions!$F$4:$F$400,4) -> 0 | D15: =C15-B15 -> 0
A16: Utilities | B16: 0 | C16: =SUMIFS(Transactions!$E$4:$E$400,Transactions!$C$4:$C$400,$A16,Transactions!$F$4:$F$400,4) -> 0 | D16: =C16-B16 -> 0
A17: Insurance | B17: 0 | C17: =SUMIFS(Transactions!$E$4:$E$400,Transactions!$C$4:$C$400,$A17,Transactions!$F$4:$F$400,4) -> 0 | D17: =C17-B17 -> 0
A18: Phone Bill | B18: 0 | C18: =SUMIFS(Transactions!$E$4:$E$400,Transactions!$C$4:$C$400,$A18,Transactions!$F$4:$F$400,4) -> 0 | D18: =C18-B18 -> 0
A19: Internet | B19: 0 | C19: =SUMIFS(Transactions!$E$4:$E$400,Transactions!$C$4:$C$400,$A19,Transactions!$F$4:$F$400,4) -> 0 | D19: =C19-B19 -> 0
A20: Subscriptions | B20: 0 | C20: =SUMIFS(Transactions!$E$4:$E$400,Transactions!$C$4:$C$400,$A20,Transactions!$F$4:$F$400,4) -> 0 | D20: =C20-B20 -> 0
A21: Car Payment | B21: 0 | C21: =SUMIFS(Transactions!$E$4:$E$400,Transactions!$C$4:$C$400,$A21,Transactions!$F$4:$F$400,4) -> 0 | D21: =C21-B21 -> 0
A22: Loan Payments | B22: 0 | C22: =SUMIFS(Transactions!$E$4:$E$400,Transactions!$C$4:$C$400,$A22,Transactions!$F$4:$F$400,4) -> 0 | D22: =C22-B22 -> 0
A23: Total Fixed Expenses | B23: =SUM(B15:B22) -> 0 | C23: =SUM(C15:C22) -> 0 | D23: =SUM(D15:D22) -> 0
A25: VARIABLE EXPENSES
A26: Groceries | B26: 0 | C26: =SUMIFS(Transactions!$E$4:$E$400,Transactions!$C$4:$C$400,$A26,Transactions!$F$4:$F$400,4) -> 0 | D26: =C26-B26 -> 0
A27: Dining Out | B27: 0 | C27: =SUMIFS(Transactions!$E$4:$E$400,Transactions!$C$4:$C$400,$A27,Transactions!$F$4:$F$400,4) -> 0 | D27: =C27-B27 -> 0
A28: Transportation / Gas | B28: 0 | C28: =SUMIFS(Transactions!$E$4:$E$400,Transactions!$C$4:$C$400,$A28,Transactions!$F$4:$F$400,4) -> 0 | D28: =C28-B28 -> 0
A29: Entertainment | B29: 0 | C29: =SUMIFS(Transactions!$E$4:$E$400,Transactions!$C$4:$C$400,$A29,Transactions!$F$4:$F$400,4) -> 0 | D29: =C29-B29 -> 0
A30: Shopping | B30: 0 | C30: =SUMIFS(Transactions!$E$4:$E$400,Transactions!$C$4:$C$400,$A30,Transactions!$F$4:$F$400,4) -> 0 | D30: =C30-B30 -> 0
A31: Personal Care | B31: 0 | C31: =SUMIFS(Transactions!$E$4:$E$400,Transactions!$C$4:$C$400,$A31,Transactions!$F$4:$F$400,4) -> 0 | D31: =C31-B31 -> 0
A32: Health / Medical | B32: 0 | C32: =SUMIFS(Transactions!$E$4:$E$400,Transactions!$C$4:$C$400,$A32,Transactions!$F$4:$F$400,4) -> 0 | D32: =C32-B32 -> 0
A33: Pet Care | B33: 0 | C33: =SUMIFS(Transactions!$E$4:$E$400,Transactions!$C$4:$C$400,$A33,Transactions!$F$4:$F$400,4) -> 0 | D33: =C33-B33 -> 0
A34: Childcare | B34: 0 | C34: =SUMIFS(Transactions!$E$4:$E$400,Transactions!$C$4:$C$400,$A34,Transactions!$F$4:$F$400,4) -> 0 | D34: =C34-B34 -> 0
A35: Gifts & Donations | B35: 0 | C35: =SUMIFS(Transactions!$E$4:$E$400,Transactions!$C$4:$C$400,$A35,Transactions!$F$4:$F$400,4) -> 0 | D35: =C35-B35 -> 0
A36: Travel | B36: 0 | C36: =SUMIFS(Transactions!$E$4:$E$400,Transactions!$C$4:$C$400,$A36,Transactions!$F$4:$F$400,4) -> 0 | D36: =C36-B36 -> 0
A37: Miscellaneous | B37: 0 | C37: =SUMIFS(Transactions!$E$4:$E$400,Transactions!$C$4:$C$400,$A37,Transactions!$F$4:$F$400,4) -> 0 | D37: =C37-B37 -> 0
A38: Total Variable Expenses | B38: =SUM(B26:B37) -> 0 | C38: =SUM(C26:C37) -> 0 | D38: =SUM(D26:D37) -> 0
A40: SAVINGS & DEBT
A41: Emergency Fund | B41: 0 | C41: =SUMIFS(Transactions!$E$4:$E$400,Transactions!$C$4:$C$400,$A41,Transactions!$F$4:$F$400,4) -> 0 | D41: =C41-B41 -> 0
A42: Retirement Savings | B42: 0 | C42: =SUMIFS(Transactions!$E$4:$E$400,Transactions!$C$4:$C$400,$A42,Transactions!$F$4:$F$400,4) -> 0 | D42: =C42-B42 -> 0
A43: Investment Contributions | B43: 0 | C43: =SUMIFS(Transactions!$E$4:$E$400,Transactions!$C$4:$C$400,$A43,Transactions!$F$4:$F$400,4) -> 0 | D43: =C43-B43 -> 0
A44: Debt Payoff | B44: 0 | C44: =SUMIFS(Transactions!$E$4:$E$400,Transactions!$C$4:$C$400,$A44,Transactions!$F$4:$F$400,4) -> 0 | D44: =C44-B44 -> 0
A45: Vacation Fund | B45: 0 | C45: =SUMIFS(Transactions!$E$4:$E$400,Transactions!$C$4:$C$400,$A45,Transactions!$F$4:$F$400,4) -> 0 | D45: =C45-B45 -> 0
A46: Other Savings | B46: 0 | C46: =SUMIFS(Transactions!$E$4:$E$400,Transactions!$C$4:$C$400,$A46,Transactions!$F$4:$F$400,4) -> 0 | D46: =C46-B46 -> 0
A47: Total Savings & Debt | B47: =SUM(B41:B46) -> 0 | C47: =SUM(C41:C46) -> 0 | D47: =SUM(D41:D46) -> 0
A49: MONTH SUMMARY
A50: Total Income | B50: =B12 -> 0 | C50: =C12 -> 0 | D50: =C50-B50 -> 0
A51: Total Expenses (Fixed + Variable) | B51: =B23+B38 -> 0 | C51: =C23+C38 -> 0 | D51: =C51-B51 -> 0
A52: Total Savings & Debt Payments | B52: =B47 -> 0 | C52: =C47 -> 0 | D52: =C52-B52 -> 0
A53: NET REMAINING (Income - Everything Else) | B53: =B50-B51-B52 -> 0 | C53: =C50-C51-C52 -> 0 | D53: =C53-B53 -> 0

Sheet May
A1: ="MAY"&" "&Welcome!$B$7&" BUDGET" -> MAY 2026 BUDGET
A2: Plan it in BUDGETED, then let ACTUAL fill in from your Transactions log.
A4: CATEGORY | B4: BUDGETED | C4: ACTUAL | D4: VARIANCE
A5: INCOME
A6: Salary | B6: 0 | C6: =SUMIFS(Transactions!$E$4:$E$400,Transactions!$C$4:$C$400,$A6,Transactions!$F$4:$F$400,5) -> 0 | D6: =C6-B6 -> 0
A7: Freelance / Side Hustle | B7: 0 | C7: =SUMIFS(Transactions!$E$4:$E$400,Transactions!$C$4:$C$400,$A7,Transactions!$F$4:$F$400,5) -> 0 | D7: =C7-B7 -> 0
A8: Bonus | B8: 0 | C8: =SUMIFS(Transactions!$E$4:$E$400,Transactions!$C$4:$C$400,$A8,Transactions!$F$4:$F$400,5) -> 0 | D8: =C8-B8 -> 0
A9: Investment Income | B9: 0 | C9: =SUMIFS(Transactions!$E$4:$E$400,Transactions!$C$4:$C$400,$A9,Transactions!$F$4:$F$400,5) -> 0 | D9: =C9-B9 -> 0
A10: Gifts Received | B10: 0 | C10: =SUMIFS(Transactions!$E$4:$E$400,Transactions!$C$4:$C$400,$A10,Transactions!$F$4:$F$400,5) -> 0 | D10: =C10-B10 -> 0
A11: Other Income | B11: 0 | C11: =SUMIFS(Transactions!$E$4:$E$400,Transactions!$C$4:$C$400,$A11,Transactions!$F$4:$F$400,5) -> 0 | D11: =C11-B11 -> 0
A12: Total Income | B12: =SUM(B6:B11) -> 0 | C12: =SUM(C6:C11) -> 0 | D12: =SUM(D6:D11) -> 0
A14: FIXED EXPENSES
A15: Rent / Mortgage | B15: 0 | C15: =SUMIFS(Transactions!$E$4:$E$400,Transactions!$C$4:$C$400,$A15,Transactions!$F$4:$F$400,5) -> 0 | D15: =C15-B15 -> 0
A16: Utilities | B16: 0 | C16: =SUMIFS(Transactions!$E$4:$E$400,Transactions!$C$4:$C$400,$A16,Transactions!$F$4:$F$400,5) -> 0 | D16: =C16-B16 -> 0
A17: Insurance | B17: 0 | C17: =SUMIFS(Transactions!$E$4:$E$400,Transactions!$C$4:$C$400,$A17,Transactions!$F$4:$F$400,5) -> 0 | D17: =C17-B17 -> 0
A18: Phone Bill | B18: 0 | C18: =SUMIFS(Transactions!$E$4:$E$400,Transactions!$C$4:$C$400,$A18,Transactions!$F$4:$F$400,5) -> 0 | D18: =C18-B18 -> 0
A19: Internet | B19: 0 | C19: =SUMIFS(Transactions!$E$4:$E$400,Transactions!$C$4:$C$400,$A19,Transactions!$F$4:$F$400,5) -> 0 | D19: =C19-B19 -> 0
A20: Subscriptions | B20: 0 | C20: =SUMIFS(Transactions!$E$4:$E$400,Transactions!$C$4:$C$400,$A20,Transactions!$F$4:$F$400,5) -> 0 | D20: =C20-B20 -> 0
A21: Car Payment | B21: 0 | C21: =SUMIFS(Transactions!$E$4:$E$400,Transactions!$C$4:$C$400,$A21,Transactions!$F$4:$F$400,5) -> 0 | D21: =C21-B21 -> 0
A22: Loan Payments | B22: 0 | C22: =SUMIFS(Transactions!$E$4:$E$400,Transactions!$C$4:$C$400,$A22,Transactions!$F$4:$F$400,5) -> 0 | D22: =C22-B22 -> 0
A23: Total Fixed Expenses | B23: =SUM(B15:B22) -> 0 | C23: =SUM(C15:C22) -> 0 | D23: =SUM(D15:D22) -> 0
A25: VARIABLE EXPENSES
A26: Groceries | B26: 0 | C26: =SUMIFS(Transactions!$E$4:$E$400,Transactions!$C$4:$C$400,$A26,Transactions!$F$4:$F$400,5) -> 0 | D26: =C26-B26 -> 0
A27: Dining Out | B27: 0 | C27: =SUMIFS(Transactions!$E$4:$E$400,Transactions!$C$4:$C$400,$A27,Transactions!$F$4:$F$400,5) -> 0 | D27: =C27-B27 -> 0
A28: Transportation / Gas | B28: 0 | C28: =SUMIFS(Transactions!$E$4:$E$400,Transactions!$C$4:$C$400,$A28,Transactions!$F$4:$F$400,5) -> 0 | D28: =C28-B28 -> 0
A29: Entertainment | B29: 0 | C29: =SUMIFS(Transactions!$E$4:$E$400,Transactions!$C$4:$C$400,$A29,Transactions!$F$4:$F$400,5) -> 0 | D29: =C29-B29 -> 0
A30: Shopping | B30: 0 | C30: =SUMIFS(Transactions!$E$4:$E$400,Transactions!$C$4:$C$400,$A30,Transactions!$F$4:$F$400,5) -> 0 | D30: =C30-B30 -> 0
A31: Personal Care | B31: 0 | C31: =SUMIFS(Transactions!$E$4:$E$400,Transactions!$C$4:$C$400,$A31,Transactions!$F$4:$F$400,5) -> 0 | D31: =C31-B31 -> 0
A32: Health / Medical | B32: 0 | C32: =SUMIFS(Transactions!$E$4:$E$400,Transactions!$C$4:$C$400,$A32,Transactions!$F$4:$F$400,5) -> 0 | D32: =C32-B32 -> 0
A33: Pet Care | B33: 0 | C33: =SUMIFS(Transactions!$E$4:$E$400,Transactions!$C$4:$C$400,$A33,Transactions!$F$4:$F$400,5) -> 0 | D33: =C33-B33 -> 0
A34: Childcare | B34: 0 | C34: =SUMIFS(Transactions!$E$4:$E$400,Transactions!$C$4:$C$400,$A34,Transactions!$F$4:$F$400,5) -> 0 | D34: =C34-B34 -> 0
A35: Gifts & Donations | B35: 0 | C35: =SUMIFS(Transactions!$E$4:$E$400,Transactions!$C$4:$C$400,$A35,Transactions!$F$4:$F$400,5) -> 0 | D35: =C35-B35 -> 0
A36: Travel | B36: 0 | C36: =SUMIFS(Transactions!$E$4:$E$400,Transactions!$C$4:$C$400,$A36,Transactions!$F$4:$F$400,5) -> 0 | D36: =C36-B36 -> 0
A37: Miscellaneous | B37: 0 | C37: =SUMIFS(Transactions!$E$4:$E$400,Transactions!$C$4:$C$400,$A37,Transactions!$F$4:$F$400,5) -> 0 | D37: =C37-B37 -> 0
A38: Total Variable Expenses | B38: =SUM(B26:B37) -> 0 | C38: =SUM(C26:C37) -> 0 | D38: =SUM(D26:D37) -> 0
A40: SAVINGS & DEBT
A41: Emergency Fund | B41: 0 | C41: =SUMIFS(Transactions!$E$4:$E$400,Transactions!$C$4:$C$400,$A41,Transactions!$F$4:$F$400,5) -> 0 | D41: =C41-B41 -> 0
A42: Retirement Savings | B42: 0 | C42: =SUMIFS(Transactions!$E$4:$E$400,Transactions!$C$4:$C$400,$A42,Transactions!$F$4:$F$400,5) -> 0 | D42: =C42-B42 -> 0
A43: Investment Contributions | B43: 0 | C43: =SUMIFS(Transactions!$E$4:$E$400,Transactions!$C$4:$C$400,$A43,Transactions!$F$4:$F$400,5) -> 0 | D43: =C43-B43 -> 0
A44: Debt Payoff | B44: 0 | C44: =SUMIFS(Transactions!$E$4:$E$400,Transactions!$C$4:$C$400,$A44,Transactions!$F$4:$F$400,5) -> 0 | D44: =C44-B44 -> 0
A45: Vacation Fund | B45: 0 | C45: =SUMIFS(Transactions!$E$4:$E$400,Transactions!$C$4:$C$400,$A45,Transactions!$F$4:$F$400,5) -> 0 | D45: =C45-B45 -> 0
A46: Other Savings | B46: 0 | C46: =SUMIFS(Transactions!$E$4:$E$400,Transactions!$C$4:$C$400,$A46,Transactions!$F$4:$F$400,5) -> 0 | D46: =C46-B46 -> 0
A47: Total Savings & Debt | B47: =SUM(B41:B46) -> 0 | C47: =SUM(C41:C46) -> 0 | D47: =SUM(D41:D46) -> 0
A49: MONTH SUMMARY
A50: Total Income | B50: =B12 -> 0 | C50: =C12 -> 0 | D50: =C50-B50 -> 0
A51: Total Expenses (Fixed + Variable) | B51: =B23+B38 -> 0 | C51: =C23+C38 -> 0 | D51: =C51-B51 -> 0
A52: Total Savings & Debt Payments | B52: =B47 -> 0 | C52: =C47 -> 0 | D52: =C52-B52 -> 0
A53: NET REMAINING (Income - Everything Else) | B53: =B50-B51-B52 -> 0 | C53: =C50-C51-C52 -> 0 | D53: =C53-B53 -> 0

Sheet Jun
A1: ="JUNE"&" "&Welcome!$B$7&" BUDGET" -> JUNE 2026 BUDGET
A2: Plan it in BUDGETED, then let ACTUAL fill in from your Transactions log.
A4: CATEGORY | B4: BUDGETED | C4: ACTUAL | D4: VARIANCE
A5: INCOME
A6: Salary | B6: 0 | C6: =SUMIFS(Transactions!$E$4:$E$400,Transactions!$C$4:$C$400,$A6,Transactions!$F$4:$F$400,6) -> 0 | D6: =C6-B6 -> 0
A7: Freelance / Side Hustle | B7: 0 | C7: =SUMIFS(Transactions!$E$4:$E$400,Transactions!$C$4:$C$400,$A7,Transactions!$F$4:$F$400,6) -> 0 | D7: =C7-B7 -> 0
A8: Bonus | B8: 0 | C8: =SUMIFS(Transactions!$E$4:$E$400,Transactions!$C$4:$C$400,$A8,Transactions!$F$4:$F$400,6) -> 0 | D8: =C8-B8 -> 0
A9: Investment Income | B9: 0 | C9: =SUMIFS(Transactions!$E$4:$E$400,Transactions!$C$4:$C$400,$A9,Transactions!$F$4:$F$400,6) -> 0 | D9: =C9-B9 -> 0
A10: Gifts Received | B10: 0 | C10: =SUMIFS(Transactions!$E$4:$E$400,Transactions!$C$4:$C$400,$A10,Transactions!$F$4:$F$400,6) -> 0 | D10: =C10-B10 -> 0
A11: Other Income | B11: 0 | C11: =SUMIFS(Transactions!$E$4:$E$400,Transactions!$C$4:$C$400,$A11,Transactions!$F$4:$F$400,6) -> 0 | D11: =C11-B11 -> 0
A12: Total Income | B12: =SUM(B6:B11) -> 0 | C12: =SUM(C6:C11) -> 0 | D12: =SUM(D6:D11) -> 0
A14: FIXED EXPENSES
A15: Rent / Mortgage | B15: 0 | C15: =SUMIFS(Transactions!$E$4:$E$400,Transactions!$C$4:$C$400,$A15,Transactions!$F$4:$F$400,6) -> 0 | D15: =C15-B15 -> 0
A16: Utilities | B16: 0 | C16: =SUMIFS(Transactions!$E$4:$E$400,Transactions!$C$4:$C$400,$A16,Transactions!$F$4:$F$400,6) -> 0 | D16: =C16-B16 -> 0
A17: Insurance | B17: 0 | C17: =SUMIFS(Transactions!$E$4:$E$400,Transactions!$C$4:$C$400,$A17,Transactions!$F$4:$F$400,6) -> 0 | D17: =C17-B17 -> 0
A18: Phone Bill | B18: 0 | C18: =SUMIFS(Transactions!$E$4:$E$400,Transactions!$C$4:$C$400,$A18,Transactions!$F$4:$F$400,6) -> 0 | D18: =C18-B18 -> 0
A19: Internet | B19: 0 | C19: =SUMIFS(Transactions!$E$4:$E$400,Transactions!$C$4:$C$400,$A19,Transactions!$F$4:$F$400,6) -> 0 | D19: =C19-B19 -> 0
A20: Subscriptions | B20: 0 | C20: =SUMIFS(Transactions!$E$4:$E$400,Transactions!$C$4:$C$400,$A20,Transactions!$F$4:$F$400,6) -> 0 | D20: =C20-B20 -> 0
A21: Car Payment | B21: 0 | C21: =SUMIFS(Transactions!$E$4:$E$400,Transactions!$C$4:$C$400,$A21,Transactions!$F$4:$F$400,6) -> 0 | D21: =C21-B21 -> 0
A22: Loan Payments | B22: 0 | C22: =SUMIFS(Transactions!$E$4:$E$400,Transactions!$C$4:$C$400,$A22,Transactions!$F$4:$F$400,6) -> 0 | D22: =C22-B22 -> 0
A23: Total Fixed Expenses | B23: =SUM(B15:B22) -> 0 | C23: =SUM(C15:C22) -> 0 | D23: =SUM(D15:D22) -> 0
A25: VARIABLE EXPENSES
A26: Groceries | B26: 0 | C26: =SUMIFS(Transactions!$E$4:$E$400,Transactions!$C$4:$C$400,$A26,Transactions!$F$4:$F$400,6) -> 0 | D26: =C26-B26 -> 0
A27: Dining Out | B27: 0 | C27: =SUMIFS(Transactions!$E$4:$E$400,Transactions!$C$4:$C$400,$A27,Transactions!$F$4:$F$400,6) -> 0 | D27: =C27-B27 -> 0
A28: Transportation / Gas | B28: 0 | C28: =SUMIFS(Transactions!$E$4:$E$400,Transactions!$C$4:$C$400,$A28,Transactions!$F$4:$F$400,6) -> 0 | D28: =C28-B28 -> 0
A29: Entertainment | B29: 0 | C29: =SUMIFS(Transactions!$E$4:$E$400,Transactions!$C$4:$C$400,$A29,Transactions!$F$4:$F$400,6) -> 0 | D29: =C29-B29 -> 0
A30: Shopping | B30: 0 | C30: =SUMIFS(Transactions!$E$4:$E$400,Transactions!$C$4:$C$400,$A30,Transactions!$F$4:$F$400,6) -> 0 | D30: =C30-B30 -> 0
A31: Personal Care | B31: 0 | C31: =SUMIFS(Transactions!$E$4:$E$400,Transactions!$C$4:$C$400,$A31,Transactions!$F$4:$F$400,6) -> 0 | D31: =C31-B31 -> 0
A32: Health / Medical | B32: 0 | C32: =SUMIFS(Transactions!$E$4:$E$400,Transactions!$C$4:$C$400,$A32,Transactions!$F$4:$F$400,6) -> 0 | D32: =C32-B32 -> 0
A33: Pet Care | B33: 0 | C33: =SUMIFS(Transactions!$E$4:$E$400,Transactions!$C$4:$C$400,$A33,Transactions!$F$4:$F$400,6) -> 0 | D33: =C33-B33 -> 0
A34: Childcare | B34: 0 | C34: =SUMIFS(Transactions!$E$4:$E$400,Transactions!$C$4:$C$400,$A34,Transactions!$F$4:$F$400,6) -> 0 | D34: =C34-B34 -> 0
A35: Gifts & Donations | B35: 0 | C35: =SUMIFS(Transactions!$E$4:$E$400,Transactions!$C$4:$C$400,$A35,Transactions!$F$4:$F$400,6) -> 0 | D35: =C35-B35 -> 0
A36: Travel | B36: 0 | C36: =SUMIFS(Transactions!$E$4:$E$400,Transactions!$C$4:$C$400,$A36,Transactions!$F$4:$F$400,6) -> 0 | D36: =C36-B36 -> 0
A37: Miscellaneous | B37: 0 | C37: =SUMIFS(Transactions!$E$4:$E$400,Transactions!$C$4:$C$400,$A37,Transactions!$F$4:$F$400,6) -> 0 | D37: =C37-B37 -> 0
A38: Total Variable Expenses | B38: =SUM(B26:B37) -> 0 | C38: =SUM(C26:C37) -> 0 | D38: =SUM(D26:D37) -> 0
A40: SAVINGS & DEBT
A41: Emergency Fund | B41: 0 | C41: =SUMIFS(Transactions!$E$4:$E$400,Transactions!$C$4:$C$400,$A41,Transactions!$F$4:$F$400,6) -> 0 | D41: =C41-B41 -> 0
A42: Retirement Savings | B42: 0 | C42: =SUMIFS(Transactions!$E$4:$E$400,Transactions!$C$4:$C$400,$A42,Transactions!$F$4:$F$400,6) -> 0 | D42: =C42-B42 -> 0
A43: Investment Contributions | B43: 0 | C43: =SUMIFS(Transactions!$E$4:$E$400,Transactions!$C$4:$C$400,$A43,Transactions!$F$4:$F$400,6) -> 0 | D43: =C43-B43 -> 0
A44: Debt Payoff | B44: 0 | C44: =SUMIFS(Transactions!$E$4:$E$400,Transactions!$C$4:$C$400,$A44,Transactions!$F$4:$F$400,6) -> 0 | D44: =C44-B44 -> 0
A45: Vacation Fund | B45: 0 | C45: =SUMIFS(Transactions!$E$4:$E$400,Transactions!$C$4:$C$400,$A45,Transactions!$F$4:$F$400,6) -> 0 | D45: =C45-B45 -> 0
A46: Other Savings | B46: 0 | C46: =SUMIFS(Transactions!$E$4:$E$400,Transactions!$C$4:$C$400,$A46,Transactions!$F$4:$F$400,6) -> 0 | D46: =C46-B46 -> 0
A47: Total Savings & Debt | B47: =SUM(B41:B46) -> 0 | C47: =SUM(C41:C46) -> 0 | D47: =SUM(D41:D46) -> 0
A49: MONTH SUMMARY
A50: Total Income | B50: =B12 -> 0 | C50: =C12 -> 0 | D50: =C50-B50 -> 0
A51: Total Expenses (Fixed + Variable) | B51: =B23+B38 -> 0 | C51: =C23+C38 -> 0 | D51: =C51-B51 -> 0
A52: Total Savings & Debt Payments | B52: =B47 -> 0 | C52: =C47 -> 0 | D52: =C52-B52 -> 0
A53: NET REMAINING (Income - Everything Else) | B53: =B50-B51-B52 -> 0 | C53: =C50-C51-C52 -> 0 | D53: =C53-B53 -> 0

Sheet Jul
A1: ="JULY"&" "&Welcome!$B$7&" BUDGET" -> JULY 2026 BUDGET
A2: Plan it in BUDGETED, then let ACTUAL fill in from your Transactions log.
A4: CATEGORY | B4: BUDGETED | C4: ACTUAL | D4: VARIANCE
A5: INCOME
A6: Salary | B6: 0 | C6: =SUMIFS(Transactions!$E$4:$E$400,Transactions!$C$4:$C$400,$A6,Transactions!$F$4:$F$400,7) -> 0 | D6: =C6-B6 -> 0
A7: Freelance / Side Hustle | B7: 0 | C7: =SUMIFS(Transactions!$E$4:$E$400,Transactions!$C$4:$C$400,$A7,Transactions!$F$4:$F$400,7) -> 0 | D7: =C7-B7 -> 0
A8: Bonus | B8: 0 | C8: =SUMIFS(Transactions!$E$4:$E$400,Transactions!$C$4:$C$400,$A8,Transactions!$F$4:$F$400,7) -> 0 | D8: =C8-B8 -> 0
A9: Investment Income | B9: 0 | C9: =SUMIFS(Transactions!$E$4:$E$400,Transactions!$C$4:$C$400,$A9,Transactions!$F$4:$F$400,7) -> 0 | D9: =C9-B9 -> 0
A10: Gifts Received | B10: 0 | C10: =SUMIFS(Transactions!$E$4:$E$400,Transactions!$C$4:$C$400,$A10,Transactions!$F$4:$F$400,7) -> 0 | D10: =C10-B10 -> 0
A11: Other Income | B11: 0 | C11: =SUMIFS(Transactions!$E$4:$E$400,Transactions!$C$4:$C$400,$A11,Transactions!$F$4:$F$400,7) -> 0 | D11: =C11-B11 -> 0
A12: Total Income | B12: =SUM(B6:B11) -> 0 | C12: =SUM(C6:C11) -> 0 | D12: =SUM(D6:D11) -> 0
A14: FIXED EXPENSES
A15: Rent / Mortgage | B15: 0 | C15: =SUMIFS(Transactions!$E$4:$E$400,Transactions!$C$4:$C$400,$A15,Transactions!$F$4:$F$400,7) -> 0 | D15: =C15-B15 -> 0
A16: Utilities | B16: 0 | C16: =SUMIFS(Transactions!$E$4:$E$400,Transactions!$C$4:$C$400,$A16,Transactions!$F$4:$F$400,7) -> 0 | D16: =C16-B16 -> 0
A17: Insurance | B17: 0 | C17: =SUMIFS(Transactions!$E$4:$E$400,Transactions!$C$4:$C$400,$A17,Transactions!$F$4:$F$400,7) -> 0 | D17: =C17-B17 -> 0
A18: Phone Bill | B18: 0 | C18: =SUMIFS(Transactions!$E$4:$E$400,Transactions!$C$4:$C$400,$A18,Transactions!$F$4:$F$400,7) -> 0 | D18: =C18-B18 -> 0
A19: Internet | B19: 0 | C19: =SUMIFS(Transactions!$E$4:$E$400,Transactions!$C$4:$C$400,$A19,Transactions!$F$4:$F$400,7) -> 0 | D19: =C19-B19 -> 0
A20: Subscriptions | B20: 0 | C20: =SUMIFS(Transactions!$E$4:$E$400,Transactions!$C$4:$C$400,$A20,Transactions!$F$4:$F$400,7) -> 0 | D20: =C20-B20 -> 0
A21: Car Payment | B21: 0 | C21: =SUMIFS(Transactions!$E$4:$E$400,Transactions!$C$4:$C$400,$A21,Transactions!$F$4:$F$400,7) -> 0 | D21: =C21-B21 -> 0
A22: Loan Payments | B22: 0 | C22: =SUMIFS(Transactions!$E$4:$E$400,Transactions!$C$4:$C$400,$A22,Transactions!$F$4:$F$400,7) -> 0 | D22: =C22-B22 -> 0
A23: Total Fixed Expenses | B23: =SUM(B15:B22) -> 0 | C23: =SUM(C15:C22) -> 0 | D23: =SUM(D15:D22) -> 0
A25: VARIABLE EXPENSES
A26: Groceries | B26: 0 | C26: =SUMIFS(Transactions!$E$4:$E$400,Transactions!$C$4:$C$400,$A26,Transactions!$F$4:$F$400,7) -> 0 | D26: =C26-B26 -> 0
A27: Dining Out | B27: 0 | C27: =SUMIFS(Transactions!$E$4:$E$400,Transactions!$C$4:$C$400,$A27,Transactions!$F$4:$F$400,7) -> 0 | D27: =C27-B27 -> 0
A28: Transportation / Gas | B28: 0 | C28: =SUMIFS(Transactions!$E$4:$E$400,Transactions!$C$4:$C$400,$A28,Transactions!$F$4:$F$400,7) -> 0 | D28: =C28-B28 -> 0
A29: Entertainment | B29: 0 | C29: =SUMIFS(Transactions!$E$4:$E$400,Transactions!$C$4:$C$400,$A29,Transactions!$F$4:$F$400,7) -> 0 | D29: =C29-B29 -> 0
A30: Shopping | B30: 0 | C30: =SUMIFS(Transactions!$E$4:$E$400,Transactions!$C$4:$C$400,$A30,Transactions!$F$4:$F$400,7) -> 0 | D30: =C30-B30 -> 0
A31: Personal Care | B31: 0 | C31: =SUMIFS(Transactions!$E$4:$E$400,Transactions!$C$4:$C$400,$A31,Transactions!$F$4:$F$400,7) -> 0 | D31: =C31-B31 -> 0
A32: Health / Medical | B32: 0 | C32: =SUMIFS(Transactions!$E$4:$E$400,Transactions!$C$4:$C$400,$A32,Transactions!$F$4:$F$400,7) -> 0 | D32: =C32-B32 -> 0
A33: Pet Care | B33: 0 | C33: =SUMIFS(Transactions!$E$4:$E$400,Transactions!$C$4:$C$400,$A33,Transactions!$F$4:$F$400,7) -> 0 | D33: =C33-B33 -> 0
A34: Childcare | B34: 0 | C34: =SUMIFS(Transactions!$E$4:$E$400,Transactions!$C$4:$C$400,$A34,Transactions!$F$4:$F$400,7) -> 0 | D34: =C34-B34 -> 0
A35: Gifts & Donations | B35: 0 | C35: =SUMIFS(Transactions!$E$4:$E$400,Transactions!$C$4:$C$400,$A35,Transactions!$F$4:$F$400,7) -> 0 | D35: =C35-B35 -> 0
A36: Travel | B36: 0 | C36: =SUMIFS(Transactions!$E$4:$E$400,Transactions!$C$4:$C$400,$A36,Transactions!$F$4:$F$400,7) -> 0 | D36: =C36-B36 -> 0
A37: Miscellaneous | B37: 0 | C37: =SUMIFS(Transactions!$E$4:$E$400,Transactions!$C$4:$C$400,$A37,Transactions!$F$4:$F$400,7) -> 0 | D37: =C37-B37 -> 0
A38: Total Variable Expenses | B38: =SUM(B26:B37) -> 0 | C38: =SUM(C26:C37) -> 0 | D38: =SUM(D26:D37) -> 0
A40: SAVINGS & DEBT
A41: Emergency Fund | B41: 0 | C41: =SUMIFS(Transactions!$E$4:$E$400,Transactions!$C$4:$C$400,$A41,Transactions!$F$4:$F$400,7) -> 0 | D41: =C41-B41 -> 0
A42: Retirement Savings | B42: 0 | C42: =SUMIFS(Transactions!$E$4:$E$400,Transactions!$C$4:$C$400,$A42,Transactions!$F$4:$F$400,7) -> 0 | D42: =C42-B42 -> 0
A43: Investment Contributions | B43: 0 | C43: =SUMIFS(Transactions!$E$4:$E$400,Transactions!$C$4:$C$400,$A43,Transactions!$F$4:$F$400,7) -> 0 | D43: =C43-B43 -> 0
A44: Debt Payoff | B44: 0 | C44: =SUMIFS(Transactions!$E$4:$E$400,Transactions!$C$4:$C$400,$A44,Transactions!$F$4:$F$400,7) -> 0 | D44: =C44-B44 -> 0
A45: Vacation Fund | B45: 0 | C45: =SUMIFS(Transactions!$E$4:$E$400,Transactions!$C$4:$C$400,$A45,Transactions!$F$4:$F$400,7) -> 0 | D45: =C45-B45 -> 0
A46: Other Savings | B46: 0 | C46: =SUMIFS(Transactions!$E$4:$E$400,Transactions!$C$4:$C$400,$A46,Transactions!$F$4:$F$400,7) -> 0 | D46: =C46-B46 -> 0
A47: Total Savings & Debt | B47: =SUM(B41:B46) -> 0 | C47: =SUM(C41:C46) -> 0 | D47: =SUM(D41:D46) -> 0
A49: MONTH SUMMARY
A50: Total Income | B50: =B12 -> 0 | C50: =C12 -> 0 | D50: =C50-B50 -> 0
A51: Total Expenses (Fixed + Variable) | B51: =B23+B38 -> 0 | C51: =C23+C38 -> 0 | D51: =C51-B51 -> 0
A52: Total Savings & Debt Payments | B52: =B47 -> 0 | C52: =C47 -> 0 | D52: =C52-B52 -> 0
A53: NET REMAINING (Income - Everything Else) | B53: =B50-B51-B52 -> 0 | C53: =C50-C51-C52 -> 0 | D53: =C53-B53 -> 0

Sheet Aug
A1: ="AUGUST"&" "&Welcome!$B$7&" BUDGET" -> AUGUST 2026 BUDGET
A2: Plan it in BUDGETED, then let ACTUAL fill in from your Transactions log.
A4: CATEGORY | B4: BUDGETED | C4: ACTUAL | D4: VARIANCE
A5: INCOME
A6: Salary | B6: 0 | C6: =SUMIFS(Transactions!$E$4:$E$400,Transactions!$C$4:$C$400,$A6,Transactions!$F$4:$F$400,8) -> 0 | D6: =C6-B6 -> 0
A7: Freelance / Side Hustle | B7: 0 | C7: =SUMIFS(Transactions!$E$4:$E$400,Transactions!$C$4:$C$400,$A7,Transactions!$F$4:$F$400,8) -> 0 | D7: =C7-B7 -> 0
A8: Bonus | B8: 0 | C8: =SUMIFS(Transactions!$E$4:$E$400,Transactions!$C$4:$C$400,$A8,Transactions!$F$4:$F$400,8) -> 0 | D8: =C8-B8 -> 0
A9: Investment Income | B9: 0 | C9: =SUMIFS(Transactions!$E$4:$E$400,Transactions!$C$4:$C$400,$A9,Transactions!$F$4:$F$400,8) -> 0 | D9: =C9-B9 -> 0
A10: Gifts Received | B10: 0 | C10: =SUMIFS(Transactions!$E$4:$E$400,Transactions!$C$4:$C$400,$A10,Transactions!$F$4:$F$400,8) -> 0 | D10: =C10-B10 -> 0
A11: Other Income | B11: 0 | C11: =SUMIFS(Transactions!$E$4:$E$400,Transactions!$C$4:$C$400,$A11,Transactions!$F$4:$F$400,8) -> 0 | D11: =C11-B11 -> 0
A12: Total Income | B12: =SUM(B6:B11) -> 0 | C12: =SUM(C6:C11) -> 0 | D12: =SUM(D6:D11) -> 0
A14: FIXED EXPENSES
A15: Rent / Mortgage | B15: 0 | C15: =SUMIFS(Transactions!$E$4:$E$400,Transactions!$C$4:$C$400,$A15,Transactions!$F$4:$F$400,8) -> 0 | D15: =C15-B15 -> 0
A16: Utilities | B16: 0 | C16: =SUMIFS(Transactions!$E$4:$E$400,Transactions!$C$4:$C$400,$A16,Transactions!$F$4:$F$400,8) -> 0 | D16: =C16-B16 -> 0
A17: Insurance | B17: 0 | C17: =SUMIFS(Transactions!$E$4:$E$400,Transactions!$C$4:$C$400,$A17,Transactions!$F$4:$F$400,8) -> 0 | D17: =C17-B17 -> 0
A18: Phone Bill | B18: 0 | C18: =SUMIFS(Transactions!$E$4:$E$400,Transactions!$C$4:$C$400,$A18,Transactions!$F$4:$F$400,8) -> 0 | D18: =C18-B18 -> 0
A19: Internet | B19: 0 | C19: =SUMIFS(Transactions!$E$4:$E$400,Transactions!$C$4:$C$400,$A19,Transactions!$F$4:$F$400,8) -> 0 | D19: =C19-B19 -> 0
A20: Subscriptions | B20: 0 | C20: =SUMIFS(Transactions!$E$4:$E$400,Transactions!$C$4:$C$400,$A20,Transactions!$F$4:$F$400,8) -> 0 | D20: =C20-B20 -> 0
A21: Car Payment | B21: 0 | C21: =SUMIFS(Transactions!$E$4:$E$400,Transactions!$C$4:$C$400,$A21,Transactions!$F$4:$F$400,8) -> 0 | D21: =C21-B21 -> 0
A22: Loan Payments | B22: 0 | C22: =SUMIFS(Transactions!$E$4:$E$400,Transactions!$C$4:$C$400,$A22,Transactions!$F$4:$F$400,8) -> 0 | D22: =C22-B22 -> 0
A23: Total Fixed Expenses | B23: =SUM(B15:B22) -> 0 | C23: =SUM(C15:C22) -> 0 | D23: =SUM(D15:D22) -> 0
A25: VARIABLE EXPENSES
A26: Groceries | B26: 0 | C26: =SUMIFS(Transactions!$E$4:$E$400,Transactions!$C$4:$C$400,$A26,Transactions!$F$4:$F$400,8) -> 0 | D26: =C26-B26 -> 0
A27: Dining Out | B27: 0 | C27: =SUMIFS(Transactions!$E$4:$E$400,Transactions!$C$4:$C$400,$A27,Transactions!$F$4:$F$400,8) -> 0 | D27: =C27-B27 -> 0
A28: Transportation / Gas | B28: 0 | C28: =SUMIFS(Transactions!$E$4:$E$400,Transactions!$C$4:$C$400,$A28,Transactions!$F$4:$F$400,8) -> 0 | D28: =C28-B28 -> 0
A29: Entertainment | B29: 0 | C29: =SUMIFS(Transactions!$E$4:$E$400,Transactions!$C$4:$C$400,$A29,Transactions!$F$4:$F$400,8) -> 0 | D29: =C29-B29 -> 0
A30: Shopping | B30: 0 | C30: =SUMIFS(Transactions!$E$4:$E$400,Transactions!$C$4:$C$400,$A30,Transactions!$F$4:$F$400,8) -> 0 | D30: =C30-B30 -> 0
A31: Personal Care | B31: 0 | C31: =SUMIFS(Transactions!$E$4:$E$400,Transactions!$C$4:$C$400,$A31,Transactions!$F$4:$F$400,8) -> 0 | D31: =C31-B31 -> 0
A32: Health / Medical | B32: 0 | C32: =SUMIFS(Transactions!$E$4:$E$400,Transactions!$C$4:$C$400,$A32,Transactions!$F$4:$F$400,8) -> 0 | D32: =C32-B32 -> 0
A33: Pet Care | B33: 0 | C33: =SUMIFS(Transactions!$E$4:$E$400,Transactions!$C$4:$C$400,$A33,Transactions!$F$4:$F$400,8) -> 0 | D33: =C33-B33 -> 0
A34: Childcare | B34: 0 | C34: =SUMIFS(Transactions!$E$4:$E$400,Transactions!$C$4:$C$400,$A34,Transactions!$F$4:$F$400,8) -> 0 | D34: =C34-B34 -> 0
A35: Gifts & Donations | B35: 0 | C35: =SUMIFS(Transactions!$E$4:$E$400,Transactions!$C$4:$C$400,$A35,Transactions!$F$4:$F$400,8) -> 0 | D35: =C35-B35 -> 0
A36: Travel | B36: 0 | C36: =SUMIFS(Transactions!$E$4:$E$400,Transactions!$C$4:$C$400,$A36,Transactions!$F$4:$F$400,8) -> 0 | D36: =C36-B36 -> 0
A37: Miscellaneous | B37: 0 | C37: =SUMIFS(Transactions!$E$4:$E$400,Transactions!$C$4:$C$400,$A37,Transactions!$F$4:$F$400,8) -> 0 | D37: =C37-B37 -> 0
A38: Total Variable Expenses | B38: =SUM(B26:B37) -> 0 | C38: =SUM(C26:C37) -> 0 | D38: =SUM(D26:D37) -> 0
A40: SAVINGS & DEBT
A41: Emergency Fund | B41: 0 | C41: =SUMIFS(Transactions!$E$4:$E$400,Transactions!$C$4:$C$400,$A41,Transactions!$F$4:$F$400,8) -> 0 | D41: =C41-B41 -> 0
A42: Retirement Savings | B42: 0 | C42: =SUMIFS(Transactions!$E$4:$E$400,Transactions!$C$4:$C$400,$A42,Transactions!$F$4:$F$400,8) -> 0 | D42: =C42-B42 -> 0
A43: Investment Contributions | B43: 0 | C43: =SUMIFS(Transactions!$E$4:$E$400,Transactions!$C$4:$C$400,$A43,Transactions!$F$4:$F$400,8) -> 0 | D43: =C43-B43 -> 0
A44: Debt Payoff | B44: 0 | C44: =SUMIFS(Transactions!$E$4:$E$400,Transactions!$C$4:$C$400,$A44,Transactions!$F$4:$F$400,8) -> 0 | D44: =C44-B44 -> 0
A45: Vacation Fund | B45: 0 | C45: =SUMIFS(Transactions!$E$4:$E$400,Transactions!$C$4:$C$400,$A45,Transactions!$F$4:$F$400,8) -> 0 | D45: =C45-B45 -> 0
A46: Other Savings | B46: 0 | C46: =SUMIFS(Transactions!$E$4:$E$400,Transactions!$C$4:$C$400,$A46,Transactions!$F$4:$F$400,8) -> 0 | D46: =C46-B46 -> 0
A47: Total Savings & Debt | B47: =SUM(B41:B46) -> 0 | C47: =SUM(C41:C46) -> 0 | D47: =SUM(D41:D46) -> 0
A49: MONTH SUMMARY
A50: Total Income | B50: =B12 -> 0 | C50: =C12 -> 0 | D50: =C50-B50 -> 0
A51: Total Expenses (Fixed + Variable) | B51: =B23+B38 -> 0 | C51: =C23+C38 -> 0 | D51: =C51-B51 -> 0
A52: Total Savings & Debt Payments | B52: =B47 -> 0 | C52: =C47 -> 0 | D52: =C52-B52 -> 0
A53: NET REMAINING (Income - Everything Else) | B53: =B50-B51-B52 -> 0 | C53: =C50-C51-C52 -> 0 | D53: =C53-B53 -> 0

Sheet Sep
A1: ="SEPTEMBER"&" "&Welcome!$B$7&" BUDGET" -> SEPTEMBER 2026 BUDGET
A2: Plan it in BUDGETED, then let ACTUAL fill in from your Transactions log.
A4: CATEGORY | B4: BUDGETED | C4: ACTUAL | D4: VARIANCE
A5: INCOME
A6: Salary | B6: 0 | C6: =SUMIFS(Transactions!$E$4:$E$400,Transactions!$C$4:$C$400,$A6,Transactions!$F$4:$F$400,9) -> 0 | D6: =C6-B6 -> 0
A7: Freelance / Side Hustle | B7: 0 | C7: =SUMIFS(Transactions!$E$4:$E$400,Transactions!$C$4:$C$400,$A7,Transactions!$F$4:$F$400,9) -> 0 | D7: =C7-B7 -> 0
A8: Bonus | B8: 0 | C8: =SUMIFS(Transactions!$E$4:$E$400,Transactions!$C$4:$C$400,$A8,Transactions!$F$4:$F$400,9) -> 0 | D8: =C8-B8 -> 0
A9: Investment Income | B9: 0 | C9: =SUMIFS(Transactions!$E$4:$E$400,Transactions!$C$4:$C$400,$A9,Transactions!$F$4:$F$400,9) -> 0 | D9: =C9-B9 -> 0
A10: Gifts Received | B10: 0 | C10: =SUMIFS(Transactions!$E$4:$E$400,Transactions!$C$4:$C$400,$A10,Transactions!$F$4:$F$400,9) -> 0 | D10: =C10-B10 -> 0
A11: Other Income | B11: 0 | C11: =SUMIFS(Transactions!$E$4:$E$400,Transactions!$C$4:$C$400,$A11,Transactions!$F$4:$F$400,9) -> 0 | D11: =C11-B11 -> 0
A12: Total Income | B12: =SUM(B6:B11) -> 0 | C12: =SUM(C6:C11) -> 0 | D12: =SUM(D6:D11) -> 0
A14: FIXED EXPENSES
A15: Rent / Mortgage | B15: 0 | C15: =SUMIFS(Transactions!$E$4:$E$400,Transactions!$C$4:$C$400,$A15,Transactions!$F$4:$F$400,9) -> 0 | D15: =C15-B15 -> 0
A16: Utilities | B16: 0 | C16: =SUMIFS(Transactions!$E$4:$E$400,Transactions!$C$4:$C$400,$A16,Transactions!$F$4:$F$400,9) -> 0 | D16: =C16-B16 -> 0
A17: Insurance | B17: 0 | C17: =SUMIFS(Transactions!$E$4:$E$400,Transactions!$C$4:$C$400,$A17,Transactions!$F$4:$F$400,9) -> 0 | D17: =C17-B17 -> 0
A18: Phone Bill | B18: 0 | C18: =SUMIFS(Transactions!$E$4:$E$400,Transactions!$C$4:$C$400,$A18,Transactions!$F$4:$F$400,9) -> 0 | D18: =C18-B18 -> 0
A19: Internet | B19: 0 | C19: =SUMIFS(Transactions!$E$4:$E$400,Transactions!$C$4:$C$400,$A19,Transactions!$F$4:$F$400,9) -> 0 | D19: =C19-B19 -> 0
A20: Subscriptions | B20: 0 | C20: =SUMIFS(Transactions!$E$4:$E$400,Transactions!$C$4:$C$400,$A20,Transactions!$F$4:$F$400,9) -> 0 | D20: =C20-B20 -> 0
A21: Car Payment | B21: 0 | C21: =SUMIFS(Transactions!$E$4:$E$400,Transactions!$C$4:$C$400,$A21,Transactions!$F$4:$F$400,9) -> 0 | D21: =C21-B21 -> 0
A22: Loan Payments | B22: 0 | C22: =SUMIFS(Transactions!$E$4:$E$400,Transactions!$C$4:$C$400,$A22,Transactions!$F$4:$F$400,9) -> 0 | D22: =C22-B22 -> 0
A23: Total Fixed Expenses | B23: =SUM(B15:B22) -> 0 | C23: =SUM(C15:C22) -> 0 | D23: =SUM(D15:D22) -> 0
A25: VARIABLE EXPENSES
A26: Groceries | B26: 0 | C26: =SUMIFS(Transactions!$E$4:$E$400,Transactions!$C$4:$C$400,$A26,Transactions!$F$4:$F$400,9) -> 0 | D26: =C26-B26 -> 0
A27: Dining Out | B27: 0 | C27: =SUMIFS(Transactions!$E$4:$E$400,Transactions!$C$4:$C$400,$A27,Transactions!$F$4:$F$400,9) -> 0 | D27: =C27-B27 -> 0
A28: Transportation / Gas | B28: 0 | C28: =SUMIFS(Transactions!$E$4:$E$400,Transactions!$C$4:$C$400,$A28,Transactions!$F$4:$F$400,9) -> 0 | D28: =C28-B28 -> 0
A29: Entertainment | B29: 0 | C29: =SUMIFS(Transactions!$E$4:$E$400,Transactions!$C$4:$C$400,$A29,Transactions!$F$4:$F$400,9) -> 0 | D29: =C29-B29 -> 0
A30: Shopping | B30: 0 | C30: =SUMIFS(Transactions!$E$4:$E$400,Transactions!$C$4:$C$400,$A30,Transactions!$F$4:$F$400,9) -> 0 | D30: =C30-B30 -> 0
A31: Personal Care | B31: 0 | C31: =SUMIFS(Transactions!$E$4:$E$400,Transactions!$C$4:$C$400,$A31,Transactions!$F$4:$F$400,9) -> 0 | D31: =C31-B31 -> 0
A32: Health / Medical | B32: 0 | C32: =SUMIFS(Transactions!$E$4:$E$400,Transactions!$C$4:$C$400,$A32,Transactions!$F$4:$F$400,9) -> 0 | D32: =C32-B32 -> 0
A33: Pet Care | B33: 0 | C33: =SUMIFS(Transactions!$E$4:$E$400,Transactions!$C$4:$C$400,$A33,Transactions!$F$4:$F$400,9) -> 0 | D33: =C33-B33 -> 0
A34: Childcare | B34: 0 | C34: =SUMIFS(Transactions!$E$4:$E$400,Transactions!$C$4:$C$400,$A34,Transactions!$F$4:$F$400,9) -> 0 | D34: =C34-B34 -> 0
A35: Gifts & Donations | B35: 0 | C35: =SUMIFS(Transactions!$E$4:$E$400,Transactions!$C$4:$C$400,$A35,Transactions!$F$4:$F$400,9) -> 0 | D35: =C35-B35 -> 0
A36: Travel | B36: 0 | C36: =SUMIFS(Transactions!$E$4:$E$400,Transactions!$C$4:$C$400,$A36,Transactions!$F$4:$F$400,9) -> 0 | D36: =C36-B36 -> 0
A37: Miscellaneous | B37: 0 | C37: =SUMIFS(Transactions!$E$4:$E$400,Transactions!$C$4:$C$400,$A37,Transactions!$F$4:$F$400,9) -> 0 | D37: =C37-B37 -> 0
A38: Total Variable Expenses | B38: =SUM(B26:B37) -> 0 | C38: =SUM(C26:C37) -> 0 | D38: =SUM(D26:D37) -> 0
A40: SAVINGS & DEBT
A41: Emergency Fund | B41: 0 | C41: =SUMIFS(Transactions!$E$4:$E$400,Transactions!$C$4:$C$400,$A41,Transactions!$F$4:$F$400,9) -> 0 | D41: =C41-B41 -> 0
A42: Retirement Savings | B42: 0 | C42: =SUMIFS(Transactions!$E$4:$E$400,Transactions!$C$4:$C$400,$A42,Transactions!$F$4:$F$400,9) -> 0 | D42: =C42-B42 -> 0
A43: Investment Contributions | B43: 0 | C43: =SUMIFS(Transactions!$E$4:$E$400,Transactions!$C$4:$C$400,$A43,Transactions!$F$4:$F$400,9) -> 0 | D43: =C43-B43 -> 0
A44: Debt Payoff | B44: 0 | C44: =SUMIFS(Transactions!$E$4:$E$400,Transactions!$C$4:$C$400,$A44,Transactions!$F$4:$F$400,9) -> 0 | D44: =C44-B44 -> 0
A45: Vacation Fund | B45: 0 | C45: =SUMIFS(Transactions!$E$4:$E$400,Transactions!$C$4:$C$400,$A45,Transactions!$F$4:$F$400,9) -> 0 | D45: =C45-B45 -> 0
A46: Other Savings | B46: 0 | C46: =SUMIFS(Transactions!$E$4:$E$400,Transactions!$C$4:$C$400,$A46,Transactions!$F$4:$F$400,9) -> 0 | D46: =C46-B46 -> 0
A47: Total Savings & Debt | B47: =SUM(B41:B46) -> 0 | C47: =SUM(C41:C46) -> 0 | D47: =SUM(D41:D46) -> 0
A49: MONTH SUMMARY
A50: Total Income | B50: =B12 -> 0 | C50: =C12 -> 0 | D50: =C50-B50 -> 0
A51: Total Expenses (Fixed + Variable) | B51: =B23+B38 -> 0 | C51: =C23+C38 -> 0 | D51: =C51-B51 -> 0
A52: Total Savings & Debt Payments | B52: =B47 -> 0 | C52: =C47 -> 0 | D52: =C52-B52 -> 0
A53: NET REMAINING (Income - Everything Else) | B53: =B50-B51-B52 -> 0 | C53: =C50-C51-C52 -> 0 | D53: =C53-B53 -> 0

Sheet Oct
A1: ="OCTOBER"&" "&Welcome!$B$7&" BUDGET" -> OCTOBER 2026 BUDGET
A2: Plan it in BUDGETED, then let ACTUAL fill in from your Transactions log.
A4: CATEGORY | B4: BUDGETED | C4: ACTUAL | D4: VARIANCE
A5: INCOME
A6: Salary | B6: 0 | C6: =SUMIFS(Transactions!$E$4:$E$400,Transactions!$C$4:$C$400,$A6,Transactions!$F$4:$F$400,10) -> 0 | D6: =C6-B6 -> 0
A7: Freelance / Side Hustle | B7: 0 | C7: =SUMIFS(Transactions!$E$4:$E$400,Transactions!$C$4:$C$400,$A7,Transactions!$F$4:$F$400,10) -> 0 | D7: =C7-B7 -> 0
A8: Bonus | B8: 0 | C8: =SUMIFS(Transactions!$E$4:$E$400,Transactions!$C$4:$C$400,$A8,Transactions!$F$4:$F$400,10) -> 0 | D8: =C8-B8 -> 0
A9: Investment Income | B9: 0 | C9: =SUMIFS(Transactions!$E$4:$E$400,Transactions!$C$4:$C$400,$A9,Transactions!$F$4:$F$400,10) -> 0 | D9: =C9-B9 -> 0
A10: Gifts Received | B10: 0 | C10: =SUMIFS(Transactions!$E$4:$E$400,Transactions!$C$4:$C$400,$A10,Transactions!$F$4:$F$400,10) -> 0 | D10: =C10-B10 -> 0
A11: Other Income | B11: 0 | C11: =SUMIFS(Transactions!$E$4:$E$400,Transactions!$C$4:$C$400,$A11,Transactions!$F$4:$F$400,10) -> 0 | D11: =C11-B11 -> 0
A12: Total Income | B12: =SUM(B6:B11) -> 0 | C12: =SUM(C6:C11) -> 0 | D12: =SUM(D6:D11) -> 0
A14: FIXED EXPENSES
A15: Rent / Mortgage | B15: 0 | C15: =SUMIFS(Transactions!$E$4:$E$400,Transactions!$C$4:$C$400,$A15,Transactions!$F$4:$F$400,10) -> 0 | D15: =C15-B15 -> 0
A16: Utilities | B16: 0 | C16: =SUMIFS(Transactions!$E$4:$E$400,Transactions!$C$4:$C$400,$A16,Transactions!$F$4:$F$400,10) -> 0 | D16: =C16-B16 -> 0
A17: Insurance | B17: 0 | C17: =SUMIFS(Transactions!$E$4:$E$400,Transactions!$C$4:$C$400,$A17,Transactions!$F$4:$F$400,10) -> 0 | D17: =C17-B17 -> 0
A18: Phone Bill | B18: 0 | C18: =SUMIFS(Transactions!$E$4:$E$400,Transactions!$C$4:$C$400,$A18,Transactions!$F$4:$F$400,10) -> 0 | D18: =C18-B18 -> 0
A19: Internet | B19: 0 | C19: =SUMIFS(Transactions!$E$4:$E$400,Transactions!$C$4:$C$400,$A19,Transactions!$F$4:$F$400,10) -> 0 | D19: =C19-B19 -> 0
A20: Subscriptions | B20: 0 | C20: =SUMIFS(Transactions!$E$4:$E$400,Transactions!$C$4:$C$400,$A20,Transactions!$F$4:$F$400,10) -> 0 | D20: =C20-B20 -> 0
A21: Car Payment | B21: 0 | C21: =SUMIFS(Transactions!$E$4:$E$400,Transactions!$C$4:$C$400,$A21,Transactions!$F$4:$F$400,10) -> 0 | D21: =C21-B21 -> 0
A22: Loan Payments | B22: 0 | C22: =SUMIFS(Transactions!$E$4:$E$400,Transactions!$C$4:$C$400,$A22,Transactions!$F$4:$F$400,10) -> 0 | D22: =C22-B22 -> 0
A23: Total Fixed Expenses | B23: =SUM(B15:B22) -> 0 | C23: =SUM(C15:C22) -> 0 | D23: =SUM(D15:D22) -> 0
A25: VARIABLE EXPENSES
A26: Groceries | B26: 0 | C26: =SUMIFS(Transactions!$E$4:$E$400,Transactions!$C$4:$C$400,$A26,Transactions!$F$4:$F$400,10) -> 0 | D26: =C26-B26 -> 0
A27: Dining Out | B27: 0 | C27: =SUMIFS(Transactions!$E$4:$E$400,Transactions!$C$4:$C$400,$A27,Transactions!$F$4:$F$400,10) -> 0 | D27: =C27-B27 -> 0
A28: Transportation / Gas | B28: 0 | C28: =SUMIFS(Transactions!$E$4:$E$400,Transactions!$C$4:$C$400,$A28,Transactions!$F$4:$F$400,10) -> 0 | D28: =C28-B28 -> 0
A29: Entertainment | B29: 0 | C29: =SUMIFS(Transactions!$E$4:$E$400,Transactions!$C$4:$C$400,$A29,Transactions!$F$4:$F$400,10) -> 0 | D29: =C29-B29 -> 0
A30: Shopping | B30: 0 | C30: =SUMIFS(Transactions!$E$4:$E$400,Transactions!$C$4:$C$400,$A30,Transactions!$F$4:$F$400,10) -> 0 | D30: =C30-B30 -> 0
A31: Personal Care | B31: 0 | C31: =SUMIFS(Transactions!$E$4:$E$400,Transactions!$C$4:$C$400,$A31,Transactions!$F$4:$F$400,10) -> 0 | D31: =C31-B31 -> 0
A32: Health / Medical | B32: 0 | C32: =SUMIFS(Transactions!$E$4:$E$400,Transactions!$C$4:$C$400,$A32,Transactions!$F$4:$F$400,10) -> 0 | D32: =C32-B32 -> 0
A33: Pet Care | B33: 0 | C33: =SUMIFS(Transactions!$E$4:$E$400,Transactions!$C$4:$C$400,$A33,Transactions!$F$4:$F$400,10) -> 0 | D33: =C33-B33 -> 0
A34: Childcare | B34: 0 | C34: =SUMIFS(Transactions!$E$4:$E$400,Transactions!$C$4:$C$400,$A34,Transactions!$F$4:$F$400,10) -> 0 | D34: =C34-B34 -> 0
A35: Gifts & Donations | B35: 0 | C35: =SUMIFS(Transactions!$E$4:$E$400,Transactions!$C$4:$C$400,$A35,Transactions!$F$4:$F$400,10) -> 0 | D35: =C35-B35 -> 0
A36: Travel | B36: 0 | C36: =SUMIFS(Transactions!$E$4:$E$400,Transactions!$C$4:$C$400,$A36,Transactions!$F$4:$F$400,10) -> 0 | D36: =C36-B36 -> 0
A37: Miscellaneous | B37: 0 | C37: =SUMIFS(Transactions!$E$4:$E$400,Transactions!$C$4:$C$400,$A37,Transactions!$F$4:$F$400,10) -> 0 | D37: =C37-B37 -> 0
A38: Total Variable Expenses | B38: =SUM(B26:B37) -> 0 | C38: =SUM(C26:C37) -> 0 | D38: =SUM(D26:D37) -> 0
A40: SAVINGS & DEBT
A41: Emergency Fund | B41: 0 | C41: =SUMIFS(Transactions!$E$4:$E$400,Transactions!$C$4:$C$400,$A41,Transactions!$F$4:$F$400,10) -> 0 | D41: =C41-B41 -> 0
A42: Retirement Savings | B42: 0 | C42: =SUMIFS(Transactions!$E$4:$E$400,Transactions!$C$4:$C$400,$A42,Transactions!$F$4:$F$400,10) -> 0 | D42: =C42-B42 -> 0
A43: Investment Contributions | B43: 0 | C43: =SUMIFS(Transactions!$E$4:$E$400,Transactions!$C$4:$C$400,$A43,Transactions!$F$4:$F$400,10) -> 0 | D43: =C43-B43 -> 0
A44: Debt Payoff | B44: 0 | C44: =SUMIFS(Transactions!$E$4:$E$400,Transactions!$C$4:$C$400,$A44,Transactions!$F$4:$F$400,10) -> 0 | D44: =C44-B44 -> 0
A45: Vacation Fund | B45: 0 | C45: =SUMIFS(Transactions!$E$4:$E$400,Transactions!$C$4:$C$400,$A45,Transactions!$F$4:$F$400,10) -> 0 | D45: =C45-B45 -> 0
A46: Other Savings | B46: 0 | C46: =SUMIFS(Transactions!$E$4:$E$400,Transactions!$C$4:$C$400,$A46,Transactions!$F$4:$F$400,10) -> 0 | D46: =C46-B46 -> 0
A47: Total Savings & Debt | B47: =SUM(B41:B46) -> 0 | C47: =SUM(C41:C46) -> 0 | D47: =SUM(D41:D46) -> 0
A49: MONTH SUMMARY
A50: Total Income | B50: =B12 -> 0 | C50: =C12 -> 0 | D50: =C50-B50 -> 0
A51: Total Expenses (Fixed + Variable) | B51: =B23+B38 -> 0 | C51: =C23+C38 -> 0 | D51: =C51-B51 -> 0
A52: Total Savings & Debt Payments | B52: =B47 -> 0 | C52: =C47 -> 0 | D52: =C52-B52 -> 0
A53: NET REMAINING (Income - Everything Else) | B53: =B50-B51-B52 -> 0 | C53: =C50-C51-C52 -> 0 | D53: =C53-B53 -> 0

Sheet Nov
A1: ="NOVEMBER"&" "&Welcome!$B$7&" BUDGET" -> NOVEMBER 2026 BUDGET
A2: Plan it in BUDGETED, then let ACTUAL fill in from your Transactions log.
A4: CATEGORY | B4: BUDGETED | C4: ACTUAL | D4: VARIANCE
A5: INCOME
A6: Salary | B6: 0 | C6: =SUMIFS(Transactions!$E$4:$E$400,Transactions!$C$4:$C$400,$A6,Transactions!$F$4:$F$400,11) -> 0 | D6: =C6-B6 -> 0
A7: Freelance / Side Hustle | B7: 0 | C7: =SUMIFS(Transactions!$E$4:$E$400,Transactions!$C$4:$C$400,$A7,Transactions!$F$4:$F$400,11) -> 0 | D7: =C7-B7 -> 0
A8: Bonus | B8: 0 | C8: =SUMIFS(Transactions!$E$4:$E$400,Transactions!$C$4:$C$400,$A8,Transactions!$F$4:$F$400,11) -> 0 | D8: =C8-B8 -> 0
A9: Investment Income | B9: 0 | C9: =SUMIFS(Transactions!$E$4:$E$400,Transactions!$C$4:$C$400,$A9,Transactions!$F$4:$F$400,11) -> 0 | D9: =C9-B9 -> 0
A10: Gifts Received | B10: 0 | C10: =SUMIFS(Transactions!$E$4:$E$400,Transactions!$C$4:$C$400,$A10,Transactions!$F$4:$F$400,11) -> 0 | D10: =C10-B10 -> 0
A11: Other Income | B11: 0 | C11: =SUMIFS(Transactions!$E$4:$E$400,Transactions!$C$4:$C$400,$A11,Transactions!$F$4:$F$400,11) -> 0 | D11: =C11-B11 -> 0
A12: Total Income | B12: =SUM(B6:B11) -> 0 | C12: =SUM(C6:C11) -> 0 | D12: =SUM(D6:D11) -> 0
A14: FIXED EXPENSES
A15: Rent / Mortgage | B15: 0 | C15: =SUMIFS(Transactions!$E$4:$E$400,Transactions!$C$4:$C$400,$A15,Transactions!$F$4:$F$400,11) -> 0 | D15: =C15-B15 -> 0
A16: Utilities | B16: 0 | C16: =SUMIFS(Transactions!$E$4:$E$400,Transactions!$C$4:$C$400,$A16,Transactions!$F$4:$F$400,11) -> 0 | D16: =C16-B16 -> 0
A17: Insurance | B17: 0 | C17: =SUMIFS(Transactions!$E$4:$E$400,Transactions!$C$4:$C$400,$A17,Transactions!$F$4:$F$400,11) -> 0 | D17: =C17-B17 -> 0
A18: Phone Bill | B18: 0 | C18: =SUMIFS(Transactions!$E$4:$E$400,Transactions!$C$4:$C$400,$A18,Transactions!$F$4:$F$400,11) -> 0 | D18: =C18-B18 -> 0
A19: Internet | B19: 0 | C19: =SUMIFS(Transactions!$E$4:$E$400,Transactions!$C$4:$C$400,$A19,Transactions!$F$4:$F$400,11) -> 0 | D19: =C19-B19 -> 0
A20: Subscriptions | B20: 0 | C20: =SUMIFS(Transactions!$E$4:$E$400,Transactions!$C$4:$C$400,$A20,Transactions!$F$4:$F$400,11) -> 0 | D20: =C20-B20 -> 0
A21: Car Payment | B21: 0 | C21: =SUMIFS(Transactions!$E$4:$E$400,Transactions!$C$4:$C$400,$A21,Transactions!$F$4:$F$400,11) -> 0 | D21: =C21-B21 -> 0
A22: Loan Payments | B22: 0 | C22: =SUMIFS(Transactions!$E$4:$E$400,Transactions!$C$4:$C$400,$A22,Transactions!$F$4:$F$400,11) -> 0 | D22: =C22-B22 -> 0
A23: Total Fixed Expenses | B23: =SUM(B15:B22) -> 0 | C23: =SUM(C15:C22) -> 0 | D23: =SUM(D15:D22) -> 0
A25: VARIABLE EXPENSES
A26: Groceries | B26: 0 | C26: =SUMIFS(Transactions!$E$4:$E$400,Transactions!$C$4:$C$400,$A26,Transactions!$F$4:$F$400,11) -> 0 | D26: =C26-B26 -> 0
A27: Dining Out | B27: 0 | C27: =SUMIFS(Transactions!$E$4:$E$400,Transactions!$C$4:$C$400,$A27,Transactions!$F$4:$F$400,11) -> 0 | D27: =C27-B27 -> 0
A28: Transportation / Gas | B28: 0 | C28: =SUMIFS(Transactions!$E$4:$E$400,Transactions!$C$4:$C$400,$A28,Transactions!$F$4:$F$400,11) -> 0 | D28: =C28-B28 -> 0
A29: Entertainment | B29: 0 | C29: =SUMIFS(Transactions!$E$4:$E$400,Transactions!$C$4:$C$400,$A29,Transactions!$F$4:$F$400,11) -> 0 | D29: =C29-B29 -> 0
A30: Shopping | B30: 0 | C30: =SUMIFS(Transactions!$E$4:$E$400,Transactions!$C$4:$C$400,$A30,Transactions!$F$4:$F$400,11) -> 0 | D30: =C30-B30 -> 0
A31: Personal Care | B31: 0 | C31: =SUMIFS(Transactions!$E$4:$E$400,Transactions!$C$4:$C$400,$A31,Transactions!$F$4:$F$400,11) -> 0 | D31: =C31-B31 -> 0
A32: Health / Medical | B32: 0 | C32: =SUMIFS(Transactions!$E$4:$E$400,Transactions!$C$4:$C$400,$A32,Transactions!$F$4:$F$400,11) -> 0 | D32: =C32-B32 -> 0
A33: Pet Care | B33: 0 | C33: =SUMIFS(Transactions!$E$4:$E$400,Transactions!$C$4:$C$400,$A33,Transactions!$F$4:$F$400,11) -> 0 | D33: =C33-B33 -> 0
A34: Childcare | B34: 0 | C34: =SUMIFS(Transactions!$E$4:$E$400,Transactions!$C$4:$C$400,$A34,Transactions!$F$4:$F$400,11) -> 0 | D34: =C34-B34 -> 0
A35: Gifts & Donations | B35: 0 | C35: =SUMIFS(Transactions!$E$4:$E$400,Transactions!$C$4:$C$400,$A35,Transactions!$F$4:$F$400,11) -> 0 | D35: =C35-B35 -> 0
A36: Travel | B36: 0 | C36: =SUMIFS(Transactions!$E$4:$E$400,Transactions!$C$4:$C$400,$A36,Transactions!$F$4:$F$400,11) -> 0 | D36: =C36-B36 -> 0
A37: Miscellaneous | B37: 0 | C37: =SUMIFS(Transactions!$E$4:$E$400,Transactions!$C$4:$C$400,$A37,Transactions!$F$4:$F$400,11) -> 0 | D37: =C37-B37 -> 0
A38: Total Variable Expenses | B38: =SUM(B26:B37) -> 0 | C38: =SUM(C26:C37) -> 0 | D38: =SUM(D26:D37) -> 0
A40: SAVINGS & DEBT
A41: Emergency Fund | B41: 0 | C41: =SUMIFS(Transactions!$E$4:$E$400,Transactions!$C$4:$C$400,$A41,Transactions!$F$4:$F$400,11) -> 0 | D41: =C41-B41 -> 0
A42: Retirement Savings | B42: 0 | C42: =SUMIFS(Transactions!$E$4:$E$400,Transactions!$C$4:$C$400,$A42,Transactions!$F$4:$F$400,11) -> 0 | D42: =C42-B42 -> 0
A43: Investment Contributions | B43: 0 | C43: =SUMIFS(Transactions!$E$4:$E$400,Transactions!$C$4:$C$400,$A43,Transactions!$F$4:$F$400,11) -> 0 | D43: =C43-B43 -> 0
A44: Debt Payoff | B44: 0 | C44: =SUMIFS(Transactions!$E$4:$E$400,Transactions!$C$4:$C$400,$A44,Transactions!$F$4:$F$400,11) -> 0 | D44: =C44-B44 -> 0
A45: Vacation Fund | B45: 0 | C45: =SUMIFS(Transactions!$E$4:$E$400,Transactions!$C$4:$C$400,$A45,Transactions!$F$4:$F$400,11) -> 0 | D45: =C45-B45 -> 0
A46: Other Savings | B46: 0 | C46: =SUMIFS(Transactions!$E$4:$E$400,Transactions!$C$4:$C$400,$A46,Transactions!$F$4:$F$400,11) -> 0 | D46: =C46-B46 -> 0
A47: Total Savings & Debt | B47: =SUM(B41:B46) -> 0 | C47: =SUM(C41:C46) -> 0 | D47: =SUM(D41:D46) -> 0
A49: MONTH SUMMARY
A50: Total Income | B50: =B12 -> 0 | C50: =C12 -> 0 | D50: =C50-B50 -> 0
A51: Total Expenses (Fixed + Variable) | B51: =B23+B38 -> 0 | C51: =C23+C38 -> 0 | D51: =C51-B51 -> 0
A52: Total Savings & Debt Payments | B52: =B47 -> 0 | C52: =C47 -> 0 | D52: =C52-B52 -> 0
A53: NET REMAINING (Income - Everything Else) | B53: =B50-B51-B52 -> 0 | C53: =C50-C51-C52 -> 0 | D53: =C53-B53 -> 0

Sheet Dec
A1: ="DECEMBER"&" "&Welcome!$B$7&" BUDGET" -> DECEMBER 2026 BUDGET
A2: Plan it in BUDGETED, then let ACTUAL fill in from your Transactions log.
A4: CATEGORY | B4: BUDGETED | C4: ACTUAL | D4: VARIANCE
A5: INCOME
A6: Salary | B6: 0 | C6: =SUMIFS(Transactions!$E$4:$E$400,Transactions!$C$4:$C$400,$A6,Transactions!$F$4:$F$400,12) -> 0 | D6: =C6-B6 -> 0
A7: Freelance / Side Hustle | B7: 0 | C7: =SUMIFS(Transactions!$E$4:$E$400,Transactions!$C$4:$C$400,$A7,Transactions!$F$4:$F$400,12) -> 0 | D7: =C7-B7 -> 0
A8: Bonus | B8: 0 | C8: =SUMIFS(Transactions!$E$4:$E$400,Transactions!$C$4:$C$400,$A8,Transactions!$F$4:$F$400,12) -> 0 | D8: =C8-B8 -> 0
A9: Investment Income | B9: 0 | C9: =SUMIFS(Transactions!$E$4:$E$400,Transactions!$C$4:$C$400,$A9,Transactions!$F$4:$F$400,12) -> 0 | D9: =C9-B9 -> 0
A10: Gifts Received | B10: 0 | C10: =SUMIFS(Transactions!$E$4:$E$400,Transactions!$C$4:$C$400,$A10,Transactions!$F$4:$F$400,12) -> 0 | D10: =C10-B10 -> 0
A11: Other Income | B11: 0 | C11: =SUMIFS(Transactions!$E$4:$E$400,Transactions!$C$4:$C$400,$A11,Transactions!$F$4:$F$400,12) -> 0 | D11: =C11-B11 -> 0
A12: Total Income | B12: =SUM(B6:B11) -> 0 | C12: =SUM(C6:C11) -> 0 | D12: =SUM(D6:D11) -> 0
A14: FIXED EXPENSES
A15: Rent / Mortgage | B15: 0 | C15: =SUMIFS(Transactions!$E$4:$E$400,Transactions!$C$4:$C$400,$A15,Transactions!$F$4:$F$400,12) -> 0 | D15: =C15-B15 -> 0
A16: Utilities | B16: 0 | C16: =SUMIFS(Transactions!$E$4:$E$400,Transactions!$C$4:$C$400,$A16,Transactions!$F$4:$F$400,12) -> 0 | D16: =C16-B16 -> 0
A17: Insurance | B17: 0 | C17: =SUMIFS(Transactions!$E$4:$E$400,Transactions!$C$4:$C$400,$A17,Transactions!$F$4:$F$400,12) -> 0 | D17: =C17-B17 -> 0
A18: Phone Bill | B18: 0 | C18: =SUMIFS(Transactions!$E$4:$E$400,Transactions!$C$4:$C$400,$A18,Transactions!$F$4:$F$400,12) -> 0 | D18: =C18-B18 -> 0
A19: Internet | B19: 0 | C19: =SUMIFS(Transactions!$E$4:$E$400,Transactions!$C$4:$C$400,$A19,Transactions!$F$4:$F$400,12) -> 0 | D19: =C19-B19 -> 0
A20: Subscriptions | B20: 0 | C20: =SUMIFS(Transactions!$E$4:$E$400,Transactions!$C$4:$C$400,$A20,Transactions!$F$4:$F$400,12) -> 0 | D20: =C20-B20 -> 0
A21: Car Payment | B21: 0 | C21: =SUMIFS(Transactions!$E$4:$E$400,Transactions!$C$4:$C$400,$A21,Transactions!$F$4:$F$400,12) -> 0 | D21: =C21-B21 -> 0
A22: Loan Payments | B22: 0 | C22: =SUMIFS(Transactions!$E$4:$E$400,Transactions!$C$4:$C$400,$A22,Transactions!$F$4:$F$400,12) -> 0 | D22: =C22-B22 -> 0
A23: Total Fixed Expenses | B23: =SUM(B15:B22) -> 0 | C23: =SUM(C15:C22) -> 0 | D23: =SUM(D15:D22) -> 0
A25: VARIABLE EXPENSES
A26: Groceries | B26: 0 | C26: =SUMIFS(Transactions!$E$4:$E$400,Transactions!$C$4:$C$400,$A26,Transactions!$F$4:$F$400,12) -> 0 | D26: =C26-B26 -> 0
A27: Dining Out | B27: 0 | C27: =SUMIFS(Transactions!$E$4:$E$400,Transactions!$C$4:$C$400,$A27,Transactions!$F$4:$F$400,12) -> 0 | D27: =C27-B27 -> 0
A28: Transportation / Gas | B28: 0 | C28: =SUMIFS(Transactions!$E$4:$E$400,Transactions!$C$4:$C$400,$A28,Transactions!$F$4:$F$400,12) -> 0 | D28: =C28-B28 -> 0
A29: Entertainment | B29: 0 | C29: =SUMIFS(Transactions!$E$4:$E$400,Transactions!$C$4:$C$400,$A29,Transactions!$F$4:$F$400,12) -> 0 | D29: =C29-B29 -> 0
A30: Shopping | B30: 0 | C30: =SUMIFS(Transactions!$E$4:$E$400,Transactions!$C$4:$C$400,$A30,Transactions!$F$4:$F$400,12) -> 0 | D30: =C30-B30 -> 0
A31: Personal Care | B31: 0 | C31: =SUMIFS(Transactions!$E$4:$E$400,Transactions!$C$4:$C$400,$A31,Transactions!$F$4:$F$400,12) -> 0 | D31: =C31-B31 -> 0
A32: Health / Medical | B32: 0 | C32: =SUMIFS(Transactions!$E$4:$E$400,Transactions!$C$4:$C$400,$A32,Transactions!$F$4:$F$400,12) -> 0 | D32: =C32-B32 -> 0
A33: Pet Care | B33: 0 | C33: =SUMIFS(Transactions!$E$4:$E$400,Transactions!$C$4:$C$400,$A33,Transactions!$F$4:$F$400,12) -> 0 | D33: =C33-B33 -> 0
A34: Childcare | B34: 0 | C34: =SUMIFS(Transactions!$E$4:$E$400,Transactions!$C$4:$C$400,$A34,Transactions!$F$4:$F$400,12) -> 0 | D34: =C34-B34 -> 0
A35: Gifts & Donations | B35: 0 | C35: =SUMIFS(Transactions!$E$4:$E$400,Transactions!$C$4:$C$400,$A35,Transactions!$F$4:$F$400,12) -> 0 | D35: =C35-B35 -> 0
A36: Travel | B36: 0 | C36: =SUMIFS(Transactions!$E$4:$E$400,Transactions!$C$4:$C$400,$A36,Transactions!$F$4:$F$400,12) -> 0 | D36: =C36-B36 -> 0
A37: Miscellaneous | B37: 0 | C37: =SUMIFS(Transactions!$E$4:$E$400,Transactions!$C$4:$C$400,$A37,Transactions!$F$4:$F$400,12) -> 0 | D37: =C37-B37 -> 0
A38: Total Variable Expenses | B38: =SUM(B26:B37) -> 0 | C38: =SUM(C26:C37) -> 0 | D38: =SUM(D26:D37) -> 0
A40: SAVINGS & DEBT
A41: Emergency Fund | B41: 0 | C41: =SUMIFS(Transactions!$E$4:$E$400,Transactions!$C$4:$C$400,$A41,Transactions!$F$4:$F$400,12) -> 0 | D41: =C41-B41 -> 0
A42: Retirement Savings | B42: 0 | C42: =SUMIFS(Transactions!$E$4:$E$400,Transactions!$C$4:$C$400,$A42,Transactions!$F$4:$F$400,12) -> 0 | D42: =C42-B42 -> 0
A43: Investment Contributions | B43: 0 | C43: =SUMIFS(Transactions!$E$4:$E$400,Transactions!$C$4:$C$400,$A43,Transactions!$F$4:$F$400,12) -> 0 | D43: =C43-B43 -> 0
A44: Debt Payoff | B44: 0 | C44: =SUMIFS(Transactions!$E$4:$E$400,Transactions!$C$4:$C$400,$A44,Transactions!$F$4:$F$400,12) -> 0 | D44: =C44-B44 -> 0
A45: Vacation Fund | B45: 0 | C45: =SUMIFS(Transactions!$E$4:$E$400,Transactions!$C$4:$C$400,$A45,Transactions!$F$4:$F$400,12) -> 0 | D45: =C45-B45 -> 0
A46: Other Savings | B46: 0 | C46: =SUMIFS(Transactions!$E$4:$E$400,Transactions!$C$4:$C$400,$A46,Transactions!$F$4:$F$400,12) -> 0 | D46: =C46-B46 -> 0
A47: Total Savings & Debt | B47: =SUM(B41:B46) -> 0 | C47: =SUM(C41:C46) -> 0 | D47: =SUM(D41:D46) -> 0
A49: MONTH SUMMARY
A50: Total Income | B50: =B12 -> 0 | C50: =C12 -> 0 | D50: =C50-B50 -> 0
A51: Total Expenses (Fixed + Variable) | B51: =B23+B38 -> 0 | C51: =C23+C38 -> 0 | D51: =C51-B51 -> 0
A52: Total Savings & Debt Payments | B52: =B47 -> 0 | C52: =C47 -> 0 | D52: =C52-B52 -> 0
A53: NET REMAINING (Income - Everything Else) | B53: =B50-B51-B52 -> 0 | C53: =C50-C51-C52 -> 0 | D53: =C53-B53 -> 0

Sheet Annual Overview
A1: ANNUAL OVERVIEW — ACTUAL SPENDING BY MONTH
A2: Every number below is pulled automatically from the 12 monthly tabs — nothing to fill in here.
A4: CATEGORY | B4: Jan | C4: Feb | D4: Mar | E4: Apr | F4: May | G4: Jun | H4: Jul | I4: Aug | J4: Sep | K4: Oct | L4: Nov | M4: Dec | N4: TOTAL ACTUAL | O4: TOTAL BUDGETED | P4: VARIANCE
A5: INCOME
A6: Salary | B6: =Jan!C6 -> 6400 | C6: =Feb!C6 -> 0 | D6: =Mar!C6 -> 0 | E6: =Apr!C6 -> 0 | F6: =May!C6 -> 0 | G6: =Jun!C6 -> 0 | H6: =Jul!C6 -> 0 | I6: =Aug!C6 -> 0 | J6: =Sep!C6 -> 0 | K6: =Oct!C6 -> 0 | L6: =Nov!C6 -> 0 | M6: =Dec!C6 -> 0 | N6: =SUM(B6:M6) -> 6400 | O6: =Jan!B6+Feb!B6+Mar!B6+Apr!B6+May!B6+Jun!B6+Jul!B6+Aug!B6+Sep!B6+Oct!B6+Nov!B6+Dec!B6 -> 6400 | P6: =N6-O6 -> 0
A7: Freelance / Side Hustle | B7: =Jan!C7 -> 450 | C7: =Feb!C7 -> 0 | D7: =Mar!C7 -> 0 | E7: =Apr!C7 -> 0 | F7: =May!C7 -> 0 | G7: =Jun!C7 -> 0 | H7: =Jul!C7 -> 0 | I7: =Aug!C7 -> 0 | J7: =Sep!C7 -> 0 | K7: =Oct!C7 -> 0 | L7: =Nov!C7 -> 0 | M7: =Dec!C7 -> 0 | N7: =SUM(B7:M7) -> 450 | O7: =Jan!B7+Feb!B7+Mar!B7+Apr!B7+May!B7+Jun!B7+Jul!B7+Aug!B7+Sep!B7+Oct!B7+Nov!B7+Dec!B7 -> 400 | P7: =N7-O7 -> 50
A8: Bonus | B8: =Jan!C8 -> 0 | C8: =Feb!C8 -> 0 | D8: =Mar!C8 -> 0 | E8: =Apr!C8 -> 0 | F8: =May!C8 -> 0 | G8: =Jun!C8 -> 0 | H8: =Jul!C8 -> 0 | I8: =Aug!C8 -> 0 | J8: =Sep!C8 -> 0 | K8: =Oct!C8 -> 0 | L8: =Nov!C8 -> 0 | M8: =Dec!C8 -> 0 | N8: =SUM(B8:M8) -> 0 | O8: =Jan!B8+Feb!B8+Mar!B8+Apr!B8+May!B8+Jun!B8+Jul!B8+Aug!B8+Sep!B8+Oct!B8+Nov!B8+Dec!B8 -> 0 | P8: =N8-O8 -> 0
A9: Investment Income | B9: =Jan!C9 -> 0 | C9: =Feb!C9 -> 0 | D9: =Mar!C9 -> 0 | E9: =Apr!C9 -> 0 | F9: =May!C9 -> 0 | G9: =Jun!C9 -> 0 | H9: =Jul!C9 -> 0 | I9: =Aug!C9 -> 0 | J9: =Sep!C9 -> 0 | K9: =Oct!C9 -> 0 | L9: =Nov!C9 -> 0 | M9: =Dec!C9 -> 0 | N9: =SUM(B9:M9) -> 0 | O9: =Jan!B9+Feb!B9+Mar!B9+Apr!B9+May!B9+Jun!B9+Jul!B9+Aug!B9+Sep!B9+Oct!B9+Nov!B9+Dec!B9 -> 0 | P9: =N9-O9 -> 0
A10: Gifts Received | B10: =Jan!C10 -> 0 | C10: =Feb!C10 -> 0 | D10: =Mar!C10 -> 0 | E10: =Apr!C10 -> 0 | F10: =May!C10 -> 0 | G10: =Jun!C10 -> 0 | H10: =Jul!C10 -> 0 | I10: =Aug!C10 -> 0 | J10: =Sep!C10 -> 0 | K10: =Oct!C10 -> 0 | L10: =Nov!C10 -> 0 | M10: =Dec!C10 -> 0 | N10: =SUM(B10:M10) -> 0 | O10: =Jan!B10+Feb!B10+Mar!B10+Apr!B10+May!B10+Jun!B10+Jul!B10+Aug!B10+Sep!B10+Oct!B10+Nov!B10+Dec!B10 -> 0 | P10: =N10-O10 -> 0
A11: Other Income | B11: =Jan!C11 -> 0 | C11: =Feb!C11 -> 0 | D11: =Mar!C11 -> 0 | E11: =Apr!C11 -> 0 | F11: =May!C11 -> 0 | G11: =Jun!C11 -> 0 | H11: =Jul!C11 -> 0 | I11: =Aug!C11 -> 0 | J11: =Sep!C11 -> 0 | K11: =Oct!C11 -> 0 | L11: =Nov!C11 -> 0 | M11: =Dec!C11 -> 0 | N11: =SUM(B11:M11) -> 0 | O11: =Jan!B11+Feb!B11+Mar!B11+Apr!B11+May!B11+Jun!B11+Jul!B11+Aug!B11+Sep!B11+Oct!B11+Nov!B11+Dec!B11 -> 0 | P11: =N11-O11 -> 0
A12: Total Income | B12: =SUM(B6:B11) -> 6850 | C12: =SUM(C6:C11) -> 0 | D12: =SUM(D6:D11) -> 0 | E12: =SUM(E6:E11) -> 0 | F12: =SUM(F6:F11) -> 0 | G12: =SUM(G6:G11) -> 0 | H12: =SUM(H6:H11) -> 0 | I12: =SUM(I6:I11) -> 0 | ... P12: =SUM(P6:P11) -> 50
A14: FIXED EXPENSES
A15: Rent / Mortgage | B15: =Jan!C15 -> 1450 | C15: =Feb!C15 -> 0 | D15: =Mar!C15 -> 0 | E15: =Apr!C15 -> 0 | F15: =May!C15 -> 0 | G15: =Jun!C15 -> 0 | H15: =Jul!C15 -> 0 | I15: =Aug!C15 -> 0 | J15: =Sep!C15 -> 0 | K15: =Oct!C15 -> 0 | L15: =Nov!C15 -> 0 | M15: =Dec!C15 -> 0 | N15: =SUM(B15:M15) -> 1450 | O15: =Jan!B15+Feb!B15+Mar!B15+Apr!B15+May!B15+Jun!B15+Jul!B15+Aug!B15+Sep!B15+Oct!B15+Nov!B15+Dec!B15 -> 1450 | P15: =N15-O15 -> 0
A16: Utilities | B16: =Jan!C16 -> 165.32 | C16: =Feb!C16 -> 0 | D16: =Mar!C16 -> 0 | E16: =Apr!C16 -> 0 | F16: =May!C16 -> 0 | G16: =Jun!C16 -> 0 | H16: =Jul!C16 -> 0 | I16: =Aug!C16 -> 0 | J16: =Sep!C16 -> 0 | K16: =Oct!C16 -> 0 | L16: =Nov!C16 -> 0 | M16: =Dec!C16 -> 0 | N16: =SUM(B16:M16) -> 165.32 | O16: =Jan!B16+Feb!B16+Mar!B16+Apr!B16+May!B16+Jun!B16+Jul!B16+Aug!B16+Sep!B16+Oct!B16+Nov!B16+Dec!B16 -> 180 | P16: =N16-O16 -> -14.68
A17: Insurance | B17: =Jan!C17 -> 0 | C17: =Feb!C17 -> 0 | D17: =Mar!C17 -> 0 | E17: =Apr!C17 -> 0 | F17: =May!C17 -> 0 | G17: =Jun!C17 -> 0 | H17: =Jul!C17 -> 0 | I17: =Aug!C17 -> 0 | J17: =Sep!C17 -> 0 | K17: =Oct!C17 -> 0 | L17: =Nov!C17 -> 0 | M17: =Dec!C17 -> 0 | N17: =SUM(B17:M17) -> 0 | O17: =Jan!B17+Feb!B17+Mar!B17+Apr!B17+May!B17+Jun!B17+Jul!B17+Aug!B17+Sep!B17+Oct!B17+Nov!B17+Dec!B17 -> 120 | P17: =N17-O17 -> -120
A18: Phone Bill | B18: =Jan!C18 -> 0 | C18: =Feb!C18 -> 0 | D18: =Mar!C18 -> 0 | E18: =Apr!C18 -> 0 | F18: =May!C18 -> 0 | G18: =Jun!C18 -> 0 | H18: =Jul!C18 -> 0 | I18: =Aug!C18 -> 0 | J18: =Sep!C18 -> 0 | K18: =Oct!C18 -> 0 | L18: =Nov!C18 -> 0 | M18: =Dec!C18 -> 0 | N18: =SUM(B18:M18) -> 0 | O18: =Jan!B18+Feb!B18+Mar!B18+Apr!B18+May!B18+Jun!B18+Jul!B18+Aug!B18+Sep!B18+Oct!B18+Nov!B18+Dec!B18 -> 65 | P18: =N18-O18 -> -65
A19: Internet | B19: =Jan!C19 -> 0 | C19: =Feb!C19 -> 0 | D19: =Mar!C19 -> 0 | E19: =Apr!C19 -> 0 | F19: =May!C19 -> 0 | G19: =Jun!C19 -> 0 | H19: =Jul!C19 -> 0 | I19: =Aug!C19 -> 0 | J19: =Sep!C19 -> 0 | K19: =Oct!C19 -> 0 | L19: =Nov!C19 -> 0 | M19: =Dec!C19 -> 0 | N19: =SUM(B19:M19) -> 0 | O19: =Jan!B19+Feb!B19+Mar!B19+Apr!B19+May!B19+Jun!B19+Jul!B19+Aug!B19+Sep!B19+Oct!B19+Nov!B19+Dec!B19 -> 60 | P19: =N19-O19 -> -60
A20: Subscriptions | B20: =Jan!C20 -> 24.98 | C20: =Feb!C20 -> 0 | D20: =Mar!C20 -> 0 | E20: =Apr!C20 -> 0 | F20: =May!C20 -> 0 | G20: =Jun!C20 -> 0 | H20: =Jul!C20 -> 0 | I20: =Aug!C20 -> 0 | J20: =Sep!C20 -> 0 | K20: =Oct!C20 -> 0 | L20: =Nov!C20 -> 0 | M20: =Dec!C20 -> 0 | N20: =SUM(B20:M20) -> 24.98 | O20: =Jan!B20+Feb!B20+Mar!B20+Apr!B20+May!B20+Jun!B20+Jul!B20+Aug!B20+Sep!B20+Oct!B20+Nov!B20+Dec!B20 -> 35 | P20: =N20-O20 -> -10.02
A21: Car Payment | B21: =Jan!C21 -> 0 | C21: =Feb!C21 -> 0 | D21: =Mar!C21 -> 0 | E21: =Apr!C21 -> 0 | F21: =May!C21 -> 0 | G21: =Jun!C21 -> 0 | H21: =Jul!C21 -> 0 | I21: =Aug!C21 -> 0 | J21: =Sep!C21 -> 0 | K21: =Oct!C21 -> 0 | L21: =Nov!C21 -> 0 | M21: =Dec!C21 -> 0 | N21: =SUM(B21:M21) -> 0 | O21: =Jan!B21+Feb!B21+Mar!B21+Apr!B21+May!B21+Jun!B21+Jul!B21+Aug!B21+Sep!B21+Oct!B21+Nov!B21+Dec!B21 -> 320 | P21: =N21-O21 -> -320
A22: Loan Payments | B22: =Jan!C22 -> 0 | C22: =Feb!C22 -> 0 | D22: =Mar!C22 -> 0 | E22: =Apr!C22 -> 0 | F22: =May!C22 -> 0 | G22: =Jun!C22 -> 0 | H22: =Jul!C22 -> 0 | I22: =Aug!C22 -> 0 | J22: =Sep!C22 -> 0 | K22: =Oct!C22 -> 0 | L22: =Nov!C22 -> 0 | M22: =Dec!C22 -> 0 | N22: =SUM(B22:M22) -> 0 | O22: =Jan!B22+Feb!B22+Mar!B22+Apr!B22+May!B22+Jun!B22+Jul!B22+Aug!B22+Sep!B22+Oct!B22+Nov!B22+Dec!B22 -> 150 | P22: =N22-O22 -> -150
A23: Total Fixed Expenses | B23: =SUM(B15:B22) -> 1640.3 | C23: =SUM(C15:C22) -> 0 | D23: =SUM(D15:D22) -> 0 | E23: =SUM(E15:E22) -> 0 | F23: =SUM(F15:F22) -> 0 | G23: =SUM(G15:G22) -> 0 | H23: =SUM(H15:H22) -> 0 | I23: =SUM(I15:I22) -> 0 | ... P23: =SUM(P15:P22) -> -739.7
A25: VARIABLE EXPENSES
A26: Groceries | B26: =Jan!C26 -> 211.07 | C26: =Feb!C26 -> 0 | D26: =Mar!C26 -> 0 | E26: =Apr!C26 -> 0 | F26: =May!C26 -> 0 | G26: =Jun!C26 -> 0 | H26: =Jul!C26 -> 0 | I26: =Aug!C26 -> 0 | J26: =Sep!C26 -> 0 | K26: =Oct!C26 -> 0 | L26: =Nov!C26 -> 0 | M26: =Dec!C26 -> 0 | N26: =SUM(B26:M26) -> 211.07 | O26: =Jan!B26+Feb!B26+Mar!B26+Apr!B26+May!B26+Jun!B26+Jul!B26+Aug!B26+Sep!B26+Oct!B26+Nov!B26+Dec!B26 -> 450 | P26: =N26-O26 -> -238.93
A27: Dining Out | B27: =Jan!C27 -> 62.1 | C27: =Feb!C27 -> 0 | D27: =Mar!C27 -> 0 | E27: =Apr!C27 -> 0 | F27: =May!C27 -> 0 | G27: =Jun!C27 -> 0 | H27: =Jul!C27 -> 0 | I27: =Aug!C27 -> 0 | J27: =Sep!C27 -> 0 | K27: =Oct!C27 -> 0 | L27: =Nov!C27 -> 0 | M27: =Dec!C27 -> 0 | N27: =SUM(B27:M27) -> 62.1 | O27: =Jan!B27+Feb!B27+Mar!B27+Apr!B27+May!B27+Jun!B27+Jul!B27+Aug!B27+Sep!B27+Oct!B27+Nov!B27+Dec!B27 -> 150 | P27: =N27-O27 -> -87.9
A28: Transportation / Gas | B28: =Jan!C28 -> 45 | C28: =Feb!C28 -> 0 | D28: =Mar!C28 -> 0 | E28: =Apr!C28 -> 0 | F28: =May!C28 -> 0 | G28: =Jun!C28 -> 0 | H28: =Jul!C28 -> 0 | I28: =Aug!C28 -> 0 | J28: =Sep!C28 -> 0 | K28: =Oct!C28 -> 0 | L28: =Nov!C28 -> 0 | M28: =Dec!C28 -> 0 | N28: =SUM(B28:M28) -> 45 | O28: =Jan!B28+Feb!B28+Mar!B28+Apr!B28+May!B28+Jun!B28+Jul!B28+Aug!B28+Sep!B28+Oct!B28+Nov!B28+Dec!B28 -> 120 | P28: =N28-O28 -> -75
A29: Entertainment | B29: =Jan!C29 -> 0 | C29: =Feb!C29 -> 0 | D29: =Mar!C29 -> 0 | E29: =Apr!C29 -> 0 | F29: =May!C29 -> 0 | G29: =Jun!C29 -> 0 | H29: =Jul!C29 -> 0 | I29: =Aug!C29 -> 0 | J29: =Sep!C29 -> 0 | K29: =Oct!C29 -> 0 | L29: =Nov!C29 -> 0 | M29: =Dec!C29 -> 0 | N29: =SUM(B29:M29) -> 0 | O29: =Jan!B29+Feb!B29+Mar!B29+Apr!B29+May!B29+Jun!B29+Jul!B29+Aug!B29+Sep!B29+Oct!B29+Nov!B29+Dec!B29 -> 80 | P29: =N29-O29 -> -80
A30: Shopping | B30: =Jan!C30 -> 0 | C30: =Feb!C30 -> 0 | D30: =Mar!C30 -> 0 | E30: =Apr!C30 -> 0 | F30: =May!C30 -> 0 | G30: =Jun!C30 -> 0 | H30: =Jul!C30 -> 0 | I30: =Aug!C30 -> 0 | J30: =Sep!C30 -> 0 | K30: =Oct!C30 -> 0 | L30: =Nov!C30 -> 0 | M30: =Dec!C30 -> 0 | N30: =SUM(B30:M30) -> 0 | O30: =Jan!B30+Feb!B30+Mar!B30+Apr!B30+May!B30+Jun!B30+Jul!B30+Aug!B30+Sep!B30+Oct!B30+Nov!B30+Dec!B30 -> 100 | P30: =N30-O30 -> -100
A31: Personal Care | B31: =Jan!C31 -> 0 | C31: =Feb!C31 -> 0 | D31: =Mar!C31 -> 0 | E31: =Apr!C31 -> 0 | F31: =May!C31 -> 0 | G31: =Jun!C31 -> 0 | H31: =Jul!C31 -> 0 | I31: =Aug!C31 -> 0 | J31: =Sep!C31 -> 0 | K31: =Oct!C31 -> 0 | L31: =Nov!C31 -> 0 | M31: =Dec!C31 -> 0 | N31: =SUM(B31:M31) -> 0 | O31: =Jan!B31+Feb!B31+Mar!B31+Apr!B31+May!B31+Jun!B31+Jul!B31+Aug!B31+Sep!B31+Oct!B31+Nov!B31+Dec!B31 -> 50 | P31: =N31-O31 -> -50
A32: Health / Medical | B32: =Jan!C32 -> 0 | C32: =Feb!C32 -> 0 | D32: =Mar!C32 -> 0 | E32: =Apr!C32 -> 0 | F32: =May!C32 -> 0 | G32: =Jun!C32 -> 0 | H32: =Jul!C32 -> 0 | I32: =Aug!C32 -> 0 | J32: =Sep!C32 -> 0 | K32: =Oct!C32 -> 0 | L32: =Nov!C32 -> 0 | M32: =Dec!C32 -> 0 | N32: =SUM(B32:M32) -> 0 | O32: =Jan!B32+Feb!B32+Mar!B32+Apr!B32+May!B32+Jun!B32+Jul!B32+Aug!B32+Sep!B32+Oct!B32+Nov!B32+Dec!B32 -> 60 | P32: =N32-O32 -> -60
A33: Pet Care | B33: =Jan!C33 -> 0 | C33: =Feb!C33 -> 0 | D33: =Mar!C33 -> 0 | E33: =Apr!C33 -> 0 | F33: =May!C33 -> 0 | G33: =Jun!C33 -> 0 | H33: =Jul!C33 -> 0 | I33: =Aug!C33 -> 0 | J33: =Sep!C33 -> 0 | K33: =Oct!C33 -> 0 | L33: =Nov!C33 -> 0 | M33: =Dec!C33 -> 0 | N33: =SUM(B33:M33) -> 0 | O33: =Jan!B33+Feb!B33+Mar!B33+Apr!B33+May!B33+Jun!B33+Jul!B33+Aug!B33+Sep!B33+Oct!B33+Nov!B33+Dec!B33 -> 40 | P33: =N33-O33 -> -40
A34: Childcare | B34: =Jan!C34 -> 0 | C34: =Feb!C34 -> 0 | D34: =Mar!C34 -> 0 | E34: =Apr!C34 -> 0 | F34: =May!C34 -> 0 | G34: =Jun!C34 -> 0 | H34: =Jul!C34 -> 0 | I34: =Aug!C34 -> 0 | J34: =Sep!C34 -> 0 | K34: =Oct!C34 -> 0 | L34: =Nov!C34 -> 0 | M34: =Dec!C34 -> 0 | N34: =SUM(B34:M34) -> 0 | O34: =Jan!B34+Feb!B34+Mar!B34+Apr!B34+May!B34+Jun!B34+Jul!B34+Aug!B34+Sep!B34+Oct!B34+Nov!B34+Dec!B34 -> 0 | P34: =N34-O34 -> 0
A35: Gifts & Donations | B35: =Jan!C35 -> 0 | C35: =Feb!C35 -> 0 | D35: =Mar!C35 -> 0 | E35: =Apr!C35 -> 0 | F35: =May!C35 -> 0 | G35: =Jun!C35 -> 0 | H35: =Jul!C35 -> 0 | I35: =Aug!C35 -> 0 | J35: =Sep!C35 -> 0 | K35: =Oct!C35 -> 0 | L35: =Nov!C35 -> 0 | M35: =Dec!C35 -> 0 | N35: =SUM(B35:M35) -> 0 | O35: =Jan!B35+Feb!B35+Mar!B35+Apr!B35+May!B35+Jun!B35+Jul!B35+Aug!B35+Sep!B35+Oct!B35+Nov!B35+Dec!B35 -> 40 | P35: =N35-O35 -> -40
A36: Travel | B36: =Jan!C36 -> 0 | C36: =Feb!C36 -> 0 | D36: =Mar!C36 -> 0 | E36: =Apr!C36 -> 0 | F36: =May!C36 -> 0 | G36: =Jun!C36 -> 0 | H36: =Jul!C36 -> 0 | I36: =Aug!C36 -> 0 | J36: =Sep!C36 -> 0 | K36: =Oct!C36 -> 0 | L36: =Nov!C36 -> 0 | M36: =Dec!C36 -> 0 | N36: =SUM(B36:M36) -> 0 | O36: =Jan!B36+Feb!B36+Mar!B36+Apr!B36+May!B36+Jun!B36+Jul!B36+Aug!B36+Sep!B36+Oct!B36+Nov!B36+Dec!B36 -> 0 | P36: =N36-O36 -> 0
A37: Miscellaneous | B37: =Jan!C37 -> 0 | C37: =Feb!C37 -> 0 | D37: =Mar!C37 -> 0 | E37: =Apr!C37 -> 0 | F37: =May!C37 -> 0 | G37: =Jun!C37 -> 0 | H37: =Jul!C37 -> 0 | I37: =Aug!C37 -> 0 | J37: =Sep!C37 -> 0 | K37: =Oct!C37 -> 0 | L37: =Nov!C37 -> 0 | M37: =Dec!C37 -> 0 | N37: =SUM(B37:M37) -> 0 | O37: =Jan!B37+Feb!B37+Mar!B37+Apr!B37+May!B37+Jun!B37+Jul!B37+Aug!B37+Sep!B37+Oct!B37+Nov!B37+Dec!B37 -> 50 | P37: =N37-O37 -> -50
A38: Total Variable Expenses | B38: =SUM(B26:B37) -> 318.17 | C38: =SUM(C26:C37) -> 0 | D38: =SUM(D26:D37) -> 0 | E38: =SUM(E26:E37) -> 0 | F38: =SUM(F26:F37) -> 0 | G38: =SUM(G26:G37) -> 0 | H38: =SUM(H26:H37) -> 0 | I38: =SUM(I26:I37) -> 0 | ... P38: =SUM(P26:P37) -> -821.83
A40: SAVINGS & DEBT
A41: Emergency Fund | B41: =Jan!C41 -> 300 | C41: =Feb!C41 -> 0 | D41: =Mar!C41 -> 0 | E41: =Apr!C41 -> 0 | F41: =May!C41 -> 0 | G41: =Jun!C41 -> 0 | H41: =Jul!C41 -> 0 | I41: =Aug!C41 -> 0 | J41: =Sep!C41 -> 0 | K41: =Oct!C41 -> 0 | L41: =Nov!C41 -> 0 | M41: =Dec!C41 -> 0 | N41: =SUM(B41:M41) -> 300 | O41: =Jan!B41+Feb!B41+Mar!B41+Apr!B41+May!B41+Jun!B41+Jul!B41+Aug!B41+Sep!B41+Oct!B41+Nov!B41+Dec!B41 -> 300 | P41: =N41-O41 -> 0
A42: Retirement Savings | B42: =Jan!C42 -> 0 | C42: =Feb!C42 -> 0 | D42: =Mar!C42 -> 0 | E42: =Apr!C42 -> 0 | F42: =May!C42 -> 0 | G42: =Jun!C42 -> 0 | H42: =Jul!C42 -> 0 | I42: =Aug!C42 -> 0 | J42: =Sep!C42 -> 0 | K42: =Oct!C42 -> 0 | L42: =Nov!C42 -> 0 | M42: =Dec!C42 -> 0 | N42: =SUM(B42:M42) -> 0 | O42: =Jan!B42+Feb!B42+Mar!B42+Apr!B42+May!B42+Jun!B42+Jul!B42+Aug!B42+Sep!B42+Oct!B42+Nov!B42+Dec!B42 -> 200 | P42: =N42-O42 -> -200
A43: Investment Contributions | B43: =Jan!C43 -> 0 | C43: =Feb!C43 -> 0 | D43: =Mar!C43 -> 0 | E43: =Apr!C43 -> 0 | F43: =May!C43 -> 0 | G43: =Jun!C43 -> 0 | H43: =Jul!C43 -> 0 | I43: =Aug!C43 -> 0 | J43: =Sep!C43 -> 0 | K43: =Oct!C43 -> 0 | L43: =Nov!C43 -> 0 | M43: =Dec!C43 -> 0 | N43: =SUM(B43:M43) -> 0 | O43: =Jan!B43+Feb!B43+Mar!B43+Apr!B43+May!B43+Jun!B43+Jul!B43+Aug!B43+Sep!B43+Oct!B43+Nov!B43+Dec!B43 -> 0 | P43: =N43-O43 -> 0
A44: Debt Payoff | B44: =Jan!C44 -> 150 | C44: =Feb!C44 -> 0 | D44: =Mar!C44 -> 0 | E44: =Apr!C44 -> 0 | F44: =May!C44 -> 0 | G44: =Jun!C44 -> 0 | H44: =Jul!C44 -> 0 | I44: =Aug!C44 -> 0 | J44: =Sep!C44 -> 0 | K44: =Oct!C44 -> 0 | L44: =Nov!C44 -> 0 | M44: =Dec!C44 -> 0 | N44: =SUM(B44:M44) -> 150 | O44: =Jan!B44+Feb!B44+Mar!B44+Apr!B44+May!B44+Jun!B44+Jul!B44+Aug!B44+Sep!B44+Oct!B44+Nov!B44+Dec!B44 -> 150 | P44: =N44-O44 -> 0
A45: Vacation Fund | B45: =Jan!C45 -> 0 | C45: =Feb!C45 -> 0 | D45: =Mar!C45 -> 0 | E45: =Apr!C45 -> 0 | F45: =May!C45 -> 0 | G45: =Jun!C45 -> 0 | H45: =Jul!C45 -> 0 | I45: =Aug!C45 -> 0 | J45: =Sep!C45 -> 0 | K45: =Oct!C45 -> 0 | L45: =Nov!C45 -> 0 | M45: =Dec!C45 -> 0 | N45: =SUM(B45:M45) -> 0 | O45: =Jan!B45+Feb!B45+Mar!B45+Apr!B45+May!B45+Jun!B45+Jul!B45+Aug!B45+Sep!B45+Oct!B45+Nov!B45+Dec!B45 -> 50 | P45: =N45-O45 -> -50
A46: Other Savings | B46: =Jan!C46 -> 0 | C46: =Feb!C46 -> 0 | D46: =Mar!C46 -> 0 | E46: =Apr!C46 -> 0 | F46: =May!C46 -> 0 | G46: =Jun!C46 -> 0 | H46: =Jul!C46 -> 0 | I46: =Aug!C46 -> 0 | J46: =Sep!C46 -> 0 | K46: =Oct!C46 -> 0 | L46: =Nov!C46 -> 0 | M46: =Dec!C46 -> 0 | N46: =SUM(B46:M46) -> 0 | O46: =Jan!B46+Feb!B46+Mar!B46+Apr!B46+May!B46+Jun!B46+Jul!B46+Aug!B46+Sep!B46+Oct!B46+Nov!B46+Dec!B46 -> 0 | P46: =N46-O46 -> 0
A47: Total Savings & Debt | B47: =SUM(B41:B46) -> 450 | C47: =SUM(C41:C46) -> 0 | D47: =SUM(D41:D46) -> 0 | E47: =SUM(E41:E46) -> 0 | F47: =SUM(F41:F46) -> 0 | G47: =SUM(G41:G46) -> 0 | H47: =SUM(H41:H46) -> 0 | I47: =SUM(I41:I46) -> 0 | ... P47: =SUM(P41:P46) -> -250
A49: YEAR SUMMARY
A50: Total Income | B50: =B12 -> 6850 | C50: =C12 -> 0 | D50: =D12 -> 0 | E50: =E12 -> 0 | F50: =F12 -> 0 | G50: =G12 -> 0 | H50: =H12 -> 0 | I50: =I12 -> 0 | ... M50: =M12 -> 0 | N50: =SUM(B50:M50) -> 6850
A51: Total Expenses | B51: =B23+B38 -> 1958.47 | C51: =C23+C38 -> 0 | D51: =D23+D38 -> 0 | E51: =E23+E38 -> 0 | F51: =F23+F38 -> 0 | G51: =G23+G38 -> 0 | H51: =H23+H38 -> 0 | I51: =I23+I38 -> 0 | ... M51: =M23+M38 -> 0 | N51: =SUM(B51:M51) -> 1958.47
A52: Total Savings & Debt | B52: =B47 -> 450 | C52: =C47 -> 0 | D52: =D47 -> 0 | E52: =E47 -> 0 | F52: =F47 -> 0 | G52: =G47 -> 0 | H52: =H47 -> 0 | I52: =I47 -> 0 | ... M52: =M47 -> 0 | N52: =SUM(B52:M52) -> 450
A53: Net Cash Flow | B53: =B50-B51-B52 -> 4441.53 | C53: =C50-C51-C52 -> 0 | D53: =D50-D51-D52 -> 0 | E53: =E50-E51-E52 -> 0 | F53: =F50-F51-F52 -> 0 | G53: =G50-G51-G52 -> 0 | H53: =H50-H51-H52 -> 0 | I53: =I50-I51-I52 -> 0 | ... M53: =M50-M51-M52 -> 0 | N53: =SUM(B53:M53) -> 4441.53

Sheet Transactions
A1: TRANSACTIONS LOG
A2: Log every purchase and paycheck here — the whole planner updates itself from this sheet.
A3: Date | B3: Description | C3: Category | D3: Type | E3: Amount | F3: Month# | G3: Payment Method | H3: Notes
A4: 46023 | B4: January Paycheck | C4: Salary | D4: =IFERROR(INDEX(Categories!$B$2:$B$33,MATCH(C4,Categories!$A$2:$A$33,0)),"") -> Income | E4: 3200 | F4: =IF(A4="","",MONTH(A4)) -> 1 | G4: Direct Deposit
A5: 46025 | B5: Rent Payment | C5: Rent / Mortgage | D5: =IFERROR(INDEX(Categories!$B$2:$B$33,MATCH(C5,Categories!$A$2:$A$33,0)),"") -> Fixed Expense | E5: 1450 | F5: =IF(A5="","",MONTH(A5)) -> 1 | G5: Bank Transfer
A6: 46026 | B6: Electric & Gas Bill | C6: Utilities | D6: =IFERROR(INDEX(Categories!$B$2:$B$33,MATCH(C6,Categories!$A$2:$A$33,0)),"") -> Fixed Expense | E6: 165.32 | F6: =IF(A6="","",MONTH(A6)) -> 1 | G6: Debit Card
A7: 46027 | B7: Trader Joe's | C7: Groceries | D7: =IFERROR(INDEX(Categories!$B$2:$B$33,MATCH(C7,Categories!$A$2:$A$33,0)),"") -> Variable Expense | E7: 98.47 | F7: =IF(A7="","",MONTH(A7)) -> 1 | G7: Credit Card
A8: 46029 | B8: Netflix + Spotify | C8: Subscriptions | D8: =IFERROR(INDEX(Categories!$B$2:$B$33,MATCH(C8,Categories!$A$2:$A$33,0)),"") -> Fixed Expense | E8: 24.98 | F8: =IF(A8="","",MONTH(A8)) -> 1 | G8: Credit Card
A9: 46032 | B9: Gas Station | C9: Transportation / Gas | D9: =IFERROR(INDEX(Categories!$B$2:$B$33,MATCH(C9,Categories!$A$2:$A$33,0)),"") -> Variable Expense | E9: 45 | F9: =IF(A9="","",MONTH(A9)) -> 1 | G9: Debit Card
A10: 46034 | B10: Dinner with friends | C10: Dining Out | D10: =IFERROR(INDEX(Categories!$B$2:$B$33,MATCH(C10,Categories!$A$2:$A$33,0)),"") -> Variable Expense | E10: 62.1 | F10: =IF(A10="","",MONTH(A10)) -> 1 | G10: Credit Card
A11: 46037 | B11: January Paycheck | C11: Salary | D11: =IFERROR(INDEX(Categories!$B$2:$B$33,MATCH(C11,Categories!$A$2:$A$33,0)),"") -> Income | E11: 3200 | F11: =IF(A11="","",MONTH(A11)) -> 1 | G11: Direct Deposit
A12: 46037 | B12: Transfer to Savings | C12: Emergency Fund | D12: =IFERROR(INDEX(Categories!$B$2:$B$33,MATCH(C12,Categories!$A$2:$A$33,0)),"") -> Savings & Debt | E12: 300 | F12: =IF(A12="","",MONTH(A12)) -> 1 | G12: Bank Transfer
A13: 46040 | B13: Credit Card Payment | C13: Debt Payoff | D13: =IFERROR(INDEX(Categories!$B$2:$B$33,MATCH(C13,Categories!$A$2:$A$33,0)),"") -> Savings & Debt | E13: 150 | F13: =IF(A13="","",MONTH(A13)) -> 1 | G13: Bank Transfer
A14: 46044 | B14: Freelance Project | C14: Freelance / Side Hustle | D14: =IFERROR(INDEX(Categories!$B$2:$B$33,MATCH(C14,Categories!$A$2:$A$33,0)),"") -> Income | E14: 450 | F14: =IF(A14="","",MONTH(A14)) -> 1 | G14: PayPal
A15: 46049 | B15: Weekly Grocery Run | C15: Groceries | D15: =IFERROR(INDEX(Categories!$B$2:$B$33,MATCH(C15,Categories!$A$2:$A$33,0)),"") -> Variable Expense | E15: 112.6 | F15: =IF(A15="","",MONTH(A15)) -> 1 | G15: Credit Card
D16: =IFERROR(INDEX(Categories!$B$2:$B$33,MATCH(C16,Categories!$A$2:$A$33,0)),"") | F16: =IF(A16="","",MONTH(A16))
D17: =IFERROR(INDEX(Categories!$B$2:$B$33,MATCH(C17,Categories!$A$2:$A$33,0)),"") | F17: =IF(A17="","",MONTH(A17))
D18: =IFERROR(INDEX(Categories!$B$2:$B$33,MATCH(C18,Categories!$A$2:$A$33,0)),"") | F18: =IF(A18="","",MONTH(A18))
D19: =IFERROR(INDEX(Categories!$B$2:$B$33,MATCH(C19,Categories!$A$2:$A$33,0)),"") | F19: =IF(A19="","",MONTH(A19))
D20: =IFERROR(INDEX(Categories!$B$2:$B$33,MATCH(C20,Categories!$A$2:$A$33,0)),"") | F20: =IF(A20="","",MONTH(A20))
D21: =IFERROR(INDEX(Categories!$B$2:$B$33,MATCH(C21,Categories!$A$2:$A$33,0)),"") | F21: =IF(A21="","",MONTH(A21))
D22: =IFERROR(INDEX(Categories!$B$2:$B$33,MATCH(C22,Categories!$A$2:$A$33,0)),"") | F22: =IF(A22="","",MONTH(A22))
D23: =IFERROR(INDEX(Categories!$B$2:$B$33,MATCH(C23,Categories!$A$2:$A$33,0)),"") | F23: =IF(A23="","",MONTH(A23))
D24: =IFERROR(INDEX(Categories!$B$2:$B$33,MATCH(C24,Categories!$A$2:$A$33,0)),"") | F24: =IF(A24="","",MONTH(A24))
D25: =IFERROR(INDEX(Categories!$B$2:$B$33,MATCH(C25,Categories!$A$2:$A$33,0)),"") | F25: =IF(A25="","",MONTH(A25))
D26: =IFERROR(INDEX(Categories!$B$2:$B$33,MATCH(C26,Categories!$A$2:$A$33,0)),"") | F26: =IF(A26="","",MONTH(A26))
D27: =IFERROR(INDEX(Categories!$B$2:$B$33,MATCH(C27,Categories!$A$2:$A$33,0)),"") | F27: =IF(A27="","",MONTH(A27))
... D400: =IFERROR(INDEX(Categories!$B$2:$B$33,MATCH(C400,Categories!$A$2:$A$33,0)),"") | F400: =IF(A400="","",MONTH(A400))

Sheet Debt Payoff Tracker
A1: DEBT PAYOFF TRACKER
A2: List every debt, add an extra payment, and see the payoff estimate update instantly.
A3: Debt Name | B3: Balance | C3: Interest Rate | D3: Minimum Payment | E3: Extra Payment | F3: Total Monthly Payment | G3: Months to Payoff | H3: Notes
A4: Visa Credit Card | B4: 3200 | C4: 0.2199 | D4: 90 | E4: 60 | F4: =IF(D4=0,"",D4+E4) -> 150 | G4: =IF(OR(B4=0,F4=0),"",IF(F4<=B4*C4/12,"Payment too low",IF(C4=0,ROUNDUP(B4/F4,0),ROUNDUP(NPER(C4/12,-F4,B4),0)))) -> 28
A5: Student Loan | B5: 14500 | C5: 0.055 | D5: 165 | E5: 0 | F5: =IF(D5=0,"",D5+E5) -> 165 | G5: =IF(OR(B5=0,F5=0),"",IF(F5<=B5*C5/12,"Payment too low",IF(C5=0,ROUNDUP(B5/F5,0),ROUNDUP(NPER(C5/12,-F5,B5),0)))) -> 113
A6: Car Loan | B6: 9800 | C6: 0.049 | D6: 320 | E6: 0 | F6: =IF(D6=0,"",D6+E6) -> 320 | G6: =IF(OR(B6=0,F6=0),"",IF(F6<=B6*C6/12,"Payment too low",IF(C6=0,ROUNDUP(B6/F6,0),ROUNDUP(NPER(C6/12,-F6,B6),0)))) -> 33
F7: =IF(D7=0,"",D7+E7) | G7: =IF(OR(B7=0,F7=0),"",IF(F7<=B7*C7/12,"Payment too low",IF(C7=0,ROUNDUP(B7/F7,0),ROUNDUP(NPER(C7/12,-F7,B7),0))))
F8: =IF(D8=0,"",D8+E8) | G8: =IF(OR(B8=0,F8=0),"",IF(F8<=B8*C8/12,"Payment too low",IF(C8=0,ROUNDUP(B8/F8,0),ROUNDUP(NPER(C8/12,-F8,B8),0))))
F9: =IF(D9=0,"",D9+E9) | G9: =IF(OR(B9=0,F9=0),"",IF(F9<=B9*C9/12,"Payment too low",IF(C9=0,ROUNDUP(B9/F9,0),ROUNDUP(NPER(C9/12,-F9,B9),0))))
F10: =IF(D10=0,"",D10+E10) | G10: =IF(OR(B10=0,F10=0),"",IF(F10<=B10*C10/12,"Payment too low",IF(C10=0,ROUNDUP(B10/F10,0),ROUNDUP(NPER(C10/12,-F10,B10),0))))
F11: =IF(D11=0,"",D11+E11) | G11: =IF(OR(B11=0,F11=0),"",IF(F11<=B11*C11/12,"Payment too low",IF(C11=0,ROUNDUP(B11/F11,0),ROUNDUP(NPER(C11/12,-F11,B11),0))))
F12: =IF(D12=0,"",D12+E12) | G12: =IF(OR(B12=0,F12=0),"",IF(F12<=B12*C12/12,"Payment too low",IF(C12=0,ROUNDUP(B12/F12,0),ROUNDUP(NPER(C12/12,-F12,B12),0))))
F13: =IF(D13=0,"",D13+E13) | G13: =IF(OR(B13=0,F13=0),"",IF(F13<=B13*C13/12,"Payment too low",IF(C13=0,ROUNDUP(B13/F13,0),ROUNDUP(NPER(C13/12,-F13,B13),0))))
F14: =IF(D14=0,"",D14+E14) | G14: =IF(OR(B14=0,F14=0),"",IF(F14<=B14*C14/12,"Payment too low",IF(C14=0,ROUNDUP(B14/F14,0),ROUNDUP(NPER(C14/12,-F14,B14),0))))
F15: =IF(D15=0,"",D15+E15) | G15: =IF(OR(B15=0,F15=0),"",IF(F15<=B15*C15/12,"Payment too low",IF(C15=0,ROUNDUP(B15/F15,0),ROUNDUP(NPER(C15/12,-F15,B15),0))))
F16: =IF(D16=0,"",D16+E16) | G16: =IF(OR(B16=0,F16=0),"",IF(F16<=B16*C16/12,"Payment too low",IF(C16=0,ROUNDUP(B16/F16,0),ROUNDUP(NPER(C16/12,-F16,B16),0))))
F17: =IF(D17=0,"",D17+E17) | G17: =IF(OR(B17=0,F17=0),"",IF(F17<=B17*C17/12,"Payment too low",IF(C17=0,ROUNDUP(B17/F17,0),ROUNDUP(NPER(C17/12,-F17,B17),0))))
F18: =IF(D18=0,"",D18+E18) | G18: =IF(OR(B18=0,F18=0),"",IF(F18<=B18*C18/12,"Payment too low",IF(C18=0,ROUNDUP(B18/F18,0),ROUNDUP(NPER(C18/12,-F18,B18),0))))
... F20: =IF(D20=0,"",D20+E20) | G20: =IF(OR(B20=0,F20=0),"",IF(F20<=B20*C20/12,"Payment too low",IF(C20=0,ROUNDUP(B20/F20,0),ROUNDUP(NPER(C20/12,-F20,B20),0))))
A22: TOTAL DEBT | B22: =SUM(B4:B20) -> 27500
A24: Tip: pay minimums on everything, then throw every spare dollar at the smallest balance (snowball) or the highest interest rate (avalanche) as your Extra Payment.

Sheet Savings Goals
A1: SAVINGS GOALS TRACKER
A2: Turn a wish into a plan — see exactly how much to save each month.
A3: Goal Name | B3: Target Amount | C3: Current Saved | D3: Target Date | E3: % Complete | F3: Monthly Amount Needed | G3: Notes
A4: Emergency Fund | B4: 10000 | C4: 3200 | D4: 46387 | E4: =IF(B4=0,"",MIN(C4/B4,1)) -> 0.32 | F4: =IF(OR(B4=0,D4=0),"",IF(D4<=TODAY(),"Past due",IFERROR(MAX((B4-C4)/((YEAR(D4)-YEAR(TODAY()))*12+(MONTH(D4)-MONTH(TODAY()))),0),""))) -> 2266.6667
A5: Dream Vacation | B5: 4000 | C5: 650 | D5: 46235 | E5: =IF(B5=0,"",MIN(C5/B5,1)) -> 0.1625 | F5: =IF(OR(B5=0,D5=0),"",IF(D5<=TODAY(),"Past due",IFERROR(MAX((B5-C5)/((YEAR(D5)-YEAR(TODAY()))*12+(MONTH(D5)-MONTH(TODAY()))),0),""))) -> Past due
A6: New Car Down Payment | B6: 6000 | C6: 900 | D6: 46447 | E6: =IF(B6=0,"",MIN(C6/B6,1)) -> 0.15 | F6: =IF(OR(B6=0,D6=0),"",IF(D6<=TODAY(),"Past due",IFERROR(MAX((B6-C6)/((YEAR(D6)-YEAR(TODAY()))*12+(MONTH(D6)-MONTH(TODAY()))),0),""))) -> 850
E7: =IF(B7=0,"",MIN(C7/B7,1)) | F7: =IF(OR(B7=0,D7=0),"",IF(D7<=TODAY(),"Past due",IFERROR(MAX((B7-C7)/((YEAR(D7)-YEAR(TODAY()))*12+(MONTH(D7)-MONTH(TODAY()))),0),"")))
E8: =IF(B8=0,"",MIN(C8/B8,1)) | F8: =IF(OR(B8=0,D8=0),"",IF(D8<=TODAY(),"Past due",IFERROR(MAX((B8-C8)/((YEAR(D8)-YEAR(TODAY()))*12+(MONTH(D8)-MONTH(TODAY()))),0),"")))
E9: =IF(B9=0,"",MIN(C9/B9,1)) | F9: =IF(OR(B9=0,D9=0),"",IF(D9<=TODAY(),"Past due",IFERROR(MAX((B9-C9)/((YEAR(D9)-YEAR(TODAY()))*12+(MONTH(D9)-MONTH(TODAY()))),0),"")))
E10: =IF(B10=0,"",MIN(C10/B10,1)) | F10: =IF(OR(B10=0,D10=0),"",IF(D10<=TODAY(),"Past due",IFERROR(MAX((B10-C10)/((YEAR(D10)-YEAR(TODAY()))*12+(MONTH(D10)-MONTH(TODAY()))),0),"")))
E11: =IF(B11=0,"",MIN(C11/B11,1)) | F11: =IF(OR(B11=0,D11=0),"",IF(D11<=TODAY(),"Past due",IFERROR(MAX((B11-C11)/((YEAR(D11)-YEAR(TODAY()))*12+(MONTH(D11)-MONTH(TODAY()))),0),"")))
E12: =IF(B12=0,"",MIN(C12/B12,1)) | F12: =IF(OR(B12=0,D12=0),"",IF(D12<=TODAY(),"Past due",IFERROR(MAX((B12-C12)/((YEAR(D12)-YEAR(TODAY()))*12+(MONTH(D12)-MONTH(TODAY()))),0),"")))
E13: =IF(B13=0,"",MIN(C13/B13,1)) | F13: =IF(OR(B13=0,D13=0),"",IF(D13<=TODAY(),"Past due",IFERROR(MAX((B13-C13)/((YEAR(D13)-YEAR(TODAY()))*12+(MONTH(D13)-MONTH(TODAY()))),0),"")))
E14: =IF(B14=0,"",MIN(C14/B14,1)) | F14: =IF(OR(B14=0,D14=0),"",IF(D14<=TODAY(),"Past due",IFERROR(MAX((B14-C14)/((YEAR(D14)-YEAR(TODAY()))*12+(MONTH(D14)-MONTH(TODAY()))),0),"")))
E15: =IF(B15=0,"",MIN(C15/B15,1)) | F15: =IF(OR(B15=0,D15=0),"",IF(D15<=TODAY(),"Past due",IFERROR(MAX((B15-C15)/((YEAR(D15)-YEAR(TODAY()))*12+(MONTH(D15)-MONTH(TODAY()))),0),"")))
E16: =IF(B16=0,"",MIN(C16/B16,1)) | F16: =IF(OR(B16=0,D16=0),"",IF(D16<=TODAY(),"Past due",IFERROR(MAX((B16-C16)/((YEAR(D16)-YEAR(TODAY()))*12+(MONTH(D16)-MONTH(TODAY()))),0),"")))
E17: =IF(B17=0,"",MIN(C17/B17,1)) | F17: =IF(OR(B17=0,D17=0),"",IF(D17<=TODAY(),"Past due",IFERROR(MAX((B17-C17)/((YEAR(D17)-YEAR(TODAY()))*12+(MONTH(D17)-MONTH(TODAY()))),0),"")))
E18: =IF(B18=0,"",MIN(C18/B18,1)) | F18: =IF(OR(B18=0,D18=0),"",IF(D18<=TODAY(),"Past due",IFERROR(MAX((B18-C18)/((YEAR(D18)-YEAR(TODAY()))*12+(MONTH(D18)-MONTH(TODAY()))),0),"")))
A20: Monthly Amount Needed assumes even monthly contributions from today until your target date.

Sheet Categories
A1: CATEGORY | B1: TYPE
A2: Salary | B2: Income
A3: Freelance / Side Hustle | B3: Income
A4: Bonus | B4: Income
A5: Investment Income | B5: Income
A6: Gifts Received | B6: Income
A7: Other Income | B7: Income
A8: Rent / Mortgage | B8: Fixed Expense
A9: Utilities | B9: Fixed Expense
A10: Insurance | B10: Fixed Expense
A11: Phone Bill | B11: Fixed Expense
A12: Internet | B12: Fixed Expense
... A33: Other Savings | B33: Savings & Debt
